{
  "args": {
    "model": "mlp",
    "modality": "eyegaze",
    "folds": 10,
    "epochs": 100,
    "lr": 0.001,
    "weight_decay": 0.01,
    "window_before": 30.0,
    "window_after": 0.0,
    "grid_step": 3.0,
    "min_annotators": 1,
    "hidden_dim": 24,
    "dropout": 0.3,
    "seed": 42,
    "out": "/Users/marcus/Desktop/usc/VoiceOver/analysis/smile_prediction/sweep_results/mlp_eyegaze_before+during.json",
    "quiet": true
  },
  "metrics": {
    "n_samples": 267,
    "accuracy": 0.4868913857677903,
    "weighted_accuracy": 0.49441394898288676,
    "weighted_cross_entropy": 1.0333549893403584,
    "macro_f1": 0.218303946263644,
    "per_class": {
      "genuine": {
        "precision": 0.4868913857677903,
        "recall": 1.0,
        "f1": 0.654911838790932,
        "support": 130
      },
      "polite": {
        "precision": 0.0,
        "recall": 0.0,
        "f1": 0.0,
        "support": 101
      },
      "masking": {
        "precision": 0.0,
        "recall": 0.0,
        "f1": 0.0,
        "support": 36
      }
    }
  },
  "predictions": [
    {
      "task_number": 11,
      "predicted_probs": [
        0.43156731128692627,
        0.37463194131851196,
        0.19380073249340057
      ],
      "predicted_class": "genuine",
      "true_soft_label": [
        0.20000000298023224,
        0.6000000238418579,
        0.20000000298023224
      ],
      "true_top_class": "polite",
      "weight": 1.0
    },
    {
      "task_number": 27,
      "predicted_probs": [
        0.4355139434337616,
        0.37772804498672485,
        0.18675804138183594
      ],
      "predicted_class": "genuine",
      "true_soft_label": [
        0.0,
        1.0,
        0.0
      ],
      "true_top_class": "polite",
      "weight": 0.4
    },
    {
      "task_number": 33,
      "predicted_probs": [
        0.4531022310256958,
        0.3675921559333801,
        0.17930567264556885
      ],
      "predicted_class": "genuine",
      "true_soft_label": [
        0.5,
        0.5,
        0.0
      ],
      "true_top_class": "genuine",
      "weight": 1.0
    },
    {
      "task_number": 49,
      "predicted_probs": [
        0.4241732954978943,
        0.38046443462371826,
        0.19536226987838745
      ],
      "predicted_class": "genuine",
      "true_soft_label": [
        0.0,
        1.0,
        0.0
      ],
      "true_top_class": "polite",
      "weight": 0.6666666666666666
    },
    {
      "task_number": 50,
      "predicted_probs": [
        0.4266892075538635,
        0.38145333528518677,
        0.1918574720621109
      ],
      "predicted_class": "genuine",
      "true_soft_label": [
        0.0,
        1.0,
        0.0
      ],
      "true_top_class": "polite",
      "weight": 1.0
    },
    {
      "task_number": 64,
      "predicted_probs": [
        0.43616101145744324,
        0.3778912425041199,
        0.1859477162361145
      ],
      "predicted_class": "genuine",
      "true_soft_label": [
        1.0,
        0.0,
        0.0
      ],
      "true_top_class": "genuine",
      "weight": 1.0
    },
    {
      "task_number": 100,
      "predicted_probs": [
        0.43849703669548035,
        0.37447065114974976,
        0.18703226745128632
      ],
      "predicted_class": "genuine",
      "true_soft_label": [
        0.5,
        0.5,
        0.0
      ],
      "true_top_class": "genuine",
      "weight": 1.0
    },
    {
      "task_number": 121,
      "predicted_probs": [
        0.44011518359184265,
        0.3748566210269928,
        0.18502813577651978
      ],
      "predicted_class": "genuine",
      "true_soft_label": [
        0.0,
        1.0,
        0.0
      ],
      "true_top_class": "polite",
      "weight": 1.0
    },
    {
      "task_number": 125,
      "predicted_probs": [
        0.43797487020492554,
        0.3765086531639099,
        0.18551647663116455
      ],
      "predicted_class": "genuine",
      "true_soft_label": [
        0.0,
        1.0,
        0.0
      ],
      "true_top_class": "polite",
      "weight": 1.0
    },
    {
      "task_number": 131,
      "predicted_probs": [
        0.4158547520637512,
        0.38796114921569824,
        0.19618412852287292
      ],
      "predicted_class": "genuine",
      "true_soft_label": [
        1.0,
        0.0,
        0.0
      ],
      "true_top_class": "genuine",
      "weight": 1.0
    },
    {
      "task_number": 142,
      "predicted_probs": [
        0.4413326382637024,
        0.3745054006576538,
        0.1841619908809662
      ],
      "predicted_class": "genuine",
      "true_soft_label": [
        1.0,
        0.0,
        0.0
      ],
      "true_top_class": "genuine",
      "weight": 1.0
    },
    {
      "task_number": 145,
      "predicted_probs": [
        0.4460887014865875,
        0.371133953332901,
        0.18277736008167267
      ],
      "predicted_class": "genuine",
      "true_soft_label": [
        1.0,
        0.0,
        0.0
      ],
      "true_top_class": "genuine",
      "weight": 1.0
    },
    {
      "task_number": 164,
      "predicted_probs": [
        0.4378919303417206,
        0.37433597445487976,
        0.18777215480804443
      ],
      "predicted_class": "genuine",
      "true_soft_label": [
        0.0,
        1.0,
        0.0
      ],
      "true_top_class": "polite",
      "weight": 1.0
    },
    {
      "task_number": 200,
      "predicted_probs": [
        0.4480876326560974,
        0.3702344298362732,
        0.1816779524087906
      ],
      "predicted_class": "genuine",
      "true_soft_label": [
        1.0,
        0.0,
        0.0
      ],
      "true_top_class": "genuine",
      "weight": 1.0
    },
    {
      "task_number": 214,
      "predicted_probs": [
        0.4456224739551544,
        0.37207919359207153,
        0.18229828774929047
      ],
      "predicted_class": "genuine",
      "true_soft_label": [
        1.0,
        0.0,
        0.0
      ],
      "true_top_class": "genuine",
      "weight": 1.0
    },
    {
      "task_number": 257,
      "predicted_probs": [
        0.4393537640571594,
        0.37515777349472046,
        0.18548841774463654
      ],
      "predicted_class": "genuine",
      "true_soft_label": [
        1.0,
        0.0,
        0.0
      ],
      "true_top_class": "genuine",
      "weight": 1.0
    },
    {
      "task_number": 259,
      "predicted_probs": [
        0.428851455450058,
        0.37933972477912903,
        0.1918088048696518
      ],
      "predicted_class": "genuine",
      "true_soft_label": [
        1.0,
        0.0,
        0.0
      ],
      "true_top_class": "genuine",
      "weight": 1.0
    },
    {
      "task_number": 263,
      "predicted_probs": [
        0.44021785259246826,
        0.37343233823776245,
        0.1863497942686081
      ],
      "predicted_class": "genuine",
      "true_soft_label": [
        0.0,
        1.0,
        0.0
      ],
      "true_top_class": "polite",
      "weight": 1.0
    },
    {
      "task_number": 274,
      "predicted_probs": [
        0.4185342490673065,
        0.37718191742897034,
        0.2042839378118515
      ],
      "predicted_class": "genuine",
      "true_soft_label": [
        0.0,
        1.0,
        0.0
      ],
      "true_top_class": "polite",
      "weight": 1.0
    },
    {
      "task_number": 276,
      "predicted_probs": [
        0.42330387234687805,
        0.3791448473930359,
        0.19755123555660248
      ],
      "predicted_class": "genuine",
      "true_soft_label": [
        1.0,
        0.0,
        0.0
      ],
      "true_top_class": "genuine",
      "weight": 1.0
    },
    {
      "task_number": 281,
      "predicted_probs": [
        0.4411879777908325,
        0.3738915026187897,
        0.18492048978805542
      ],
      "predicted_class": "genuine",
      "true_soft_label": [
        1.0,
        0.0,
        0.0
      ],
      "true_top_class": "genuine",
      "weight": 1.0
    },
    {
      "task_number": 299,
      "predicted_probs": [
        0.44724228978157043,
        0.36975958943367004,
        0.18299812078475952
      ],
      "predicted_class": "genuine",
      "true_soft_label": [
        0.0,
        1.0,
        0.0
      ],
      "true_top_class": "polite",
      "weight": 1.0
    },
    {
      "task_number": 312,
      "predicted_probs": [
        0.4414030909538269,
        0.372516006231308,
        0.1860809028148651
      ],
      "predicted_class": "genuine",
      "true_soft_label": [
        0.0,
        1.0,
        0.0
      ],
      "true_top_class": "polite",
      "weight": 1.0
    },
    {
      "task_number": 342,
      "predicted_probs": [
        0.4316902160644531,
        0.3773108422756195,
        0.1909988969564438
      ],
      "predicted_class": "genuine",
      "true_soft_label": [
        1.0,
        0.0,
        0.0
      ],
      "true_top_class": "genuine",
      "weight": 1.0
    },
    {
      "task_number": 346,
      "predicted_probs": [
        0.44092050194740295,
        0.37283289432525635,
        0.1862465888261795
      ],
      "predicted_class": "genuine",
      "true_soft_label": [
        1.0,
        0.0,
        0.0
      ],
      "true_top_class": "genuine",
      "weight": 1.0
    },
    {
      "task_number": 377,
      "predicted_probs": [
        0.43357494473457336,
        0.37514686584472656,
        0.19127818942070007
      ],
      "predicted_class": "genuine",
      "true_soft_label": [
        0.0,
        0.0,
        1.0
      ],
      "true_top_class": "masking",
      "weight": 1.0
    },
    {
      "task_number": 380,
      "predicted_probs": [
        0.435618132352829,
        0.37280386686325073,
        0.1915779858827591
      ],
      "predicted_class": "genuine",
      "true_soft_label": [
        1.0,
        0.0,
        0.0
      ],
      "true_top_class": "genuine",
      "weight": 1.0
    },
    {
      "task_number": 7,
      "predicted_probs": [
        0.4833610951900482,
        0.35774099826812744,
        0.15889786183834076
      ],
      "predicted_class": "genuine",
      "true_soft_label": [
        0.4000000059604645,
        0.20000000298023224,
        0.4000000059604645
      ],
      "true_top_class": "genuine",
      "weight": 1.0
    },
    {
      "task_number": 12,
      "predicted_probs": [
        0.4639906585216522,
        0.3622480034828186,
        0.17376133799552917
      ],
      "predicted_class": "genuine",
      "true_soft_label": [
        0.20000000298023224,
        0.4000000059604645,
        0.4000000059604645
      ],
      "true_top_class": "polite",
      "weight": 1.0
    },
    {
      "task_number": 18,
      "predicted_probs": [
        0.454438179731369,
        0.3655191957950592,
        0.18004266917705536
      ],
      "predicted_class": "genuine",
      "true_soft_label": [
        0.0,
        1.0,
        0.0
      ],
      "true_top_class": "polite",
      "weight": 0.6
    },
    {
      "task_number": 19,
      "predicted_probs": [
        0.4686482548713684,
        0.36655834317207336,
        0.16479338705539703
      ],
      "predicted_class": "genuine",
      "true_soft_label": [
        0.20000000298023224,
        0.800000011920929,
        0.0
      ],
      "true_top_class": "polite",
      "weight": 1.0
    },
    {
      "task_number": 22,
      "predicted_probs": [
        0.4722965955734253,
        0.3587237596511841,
        0.16897964477539062
      ],
      "predicted_class": "genuine",
      "true_soft_label": [
        0.20000000298023224,
        0.4000000059604645,
        0.4000000059604645
      ],
      "true_top_class": "polite",
      "weight": 1.0
    },
    {
      "task_number": 36,
      "predicted_probs": [
        0.45618900656700134,
        0.3686378002166748,
        0.17517322301864624
      ],
      "predicted_class": "genuine",
      "true_soft_label": [
        0.0,
        0.5,
        0.5
      ],
      "true_top_class": "polite",
      "weight": 1.0
    },
    {
      "task_number": 70,
      "predicted_probs": [
        0.4774029850959778,
        0.3572407364845276,
        0.16535624861717224
      ],
      "predicted_class": "genuine",
      "true_soft_label": [
        1.0,
        0.0,
        0.0
      ],
      "true_top_class": "genuine",
      "weight": 0.6666666666666666
    },
    {
      "task_number": 77,
      "predicted_probs": [
        0.45897138118743896,
        0.3686324954032898,
        0.17239616811275482
      ],
      "predicted_class": "genuine",
      "true_soft_label": [
        0.0,
        0.5,
        0.5
      ],
      "true_top_class": "polite",
      "weight": 1.0
    },
    {
      "task_number": 79,
      "predicted_probs": [
        0.4607229232788086,
        0.3663007318973541,
        0.17297635972499847
      ],
      "predicted_class": "genuine",
      "true_soft_label": [
        0.0,
        1.0,
        0.0
      ],
      "true_top_class": "polite",
      "weight": 1.0
    },
    {
      "task_number": 90,
      "predicted_probs": [
        0.4547598659992218,
        0.37543073296546936,
        0.16980938613414764
      ],
      "predicted_class": "genuine",
      "true_soft_label": [
        0.5,
        0.0,
        0.5
      ],
      "true_top_class": "genuine",
      "weight": 1.0
    },
    {
      "task_number": 109,
      "predicted_probs": [
        0.48292049765586853,
        0.34898310899734497,
        0.16809643805027008
      ],
      "predicted_class": "genuine",
      "true_soft_label": [
        0.0,
        1.0,
        0.0
      ],
      "true_top_class": "polite",
      "weight": 1.0
    },
    {
      "task_number": 136,
      "predicted_probs": [
        0.42709627747535706,
        0.3857173025608063,
        0.18718650937080383
      ],
      "predicted_class": "genuine",
      "true_soft_label": [
        1.0,
        0.0,
        0.0
      ],
      "true_top_class": "genuine",
      "weight": 1.0
    },
    {
      "task_number": 138,
      "predicted_probs": [
        0.4430965781211853,
        0.3668695092201233,
        0.19003385305404663
      ],
      "predicted_class": "genuine",
      "true_soft_label": [
        1.0,
        0.0,
        0.0
      ],
      "true_top_class": "genuine",
      "weight": 1.0
    },
    {
      "task_number": 140,
      "predicted_probs": [
        0.46884822845458984,
        0.36493805050849915,
        0.16621379554271698
      ],
      "predicted_class": "genuine",
      "true_soft_label": [
        0.0,
        1.0,
        0.0
      ],
      "true_top_class": "polite",
      "weight": 1.0
    },
    {
      "task_number": 146,
      "predicted_probs": [
        0.4813116192817688,
        0.3560856282711029,
        0.16260270774364471
      ],
      "predicted_class": "genuine",
      "true_soft_label": [
        0.0,
        0.0,
        1.0
      ],
      "true_top_class": "masking",
      "weight": 1.0
    },
    {
      "task_number": 147,
      "predicted_probs": [
        0.48596516251564026,
        0.3553796112537384,
        0.15865522623062134
      ],
      "predicted_class": "genuine",
      "true_soft_label": [
        1.0,
        0.0,
        0.0
      ],
      "true_top_class": "genuine",
      "weight": 1.0
    },
    {
      "task_number": 148,
      "predicted_probs": [
        0.46472787857055664,
        0.36623409390449524,
        0.16903802752494812
      ],
      "predicted_class": "genuine",
      "true_soft_label": [
        1.0,
        0.0,
        0.0
      ],
      "true_top_class": "genuine",
      "weight": 1.0
    },
    {
      "task_number": 195,
      "predicted_probs": [
        0.47640782594680786,
        0.3613888919353485,
        0.16220328211784363
      ],
      "predicted_class": "genuine",
      "true_soft_label": [
        0.0,
        1.0,
        0.0
      ],
      "true_top_class": "polite",
      "weight": 1.0
    },
    {
      "task_number": 205,
      "predicted_probs": [
        0.4701387584209442,
        0.3606399595737457,
        0.16922123730182648
      ],
      "predicted_class": "genuine",
      "true_soft_label": [
        1.0,
        0.0,
        0.0
      ],
      "true_top_class": "genuine",
      "weight": 1.0
    },
    {
      "task_number": 212,
      "predicted_probs": [
        0.4784706234931946,
        0.35578709840774536,
        0.16574223339557648
      ],
      "predicted_class": "genuine",
      "true_soft_label": [
        0.0,
        1.0,
        0.0
      ],
      "true_top_class": "polite",
      "weight": 1.0
    },
    {
      "task_number": 230,
      "predicted_probs": [
        0.47588518261909485,
        0.3573235273361206,
        0.16679130494594574
      ],
      "predicted_class": "genuine",
      "true_soft_label": [
        0.0,
        1.0,
        0.0
      ],
      "true_top_class": "polite",
      "weight": 1.0
    },
    {
      "task_number": 235,
      "predicted_probs": [
        0.4732619524002075,
        0.35803863406181335,
        0.16869939863681793
      ],
      "predicted_class": "genuine",
      "true_soft_label": [
        0.0,
        1.0,
        0.0
      ],
      "true_top_class": "polite",
      "weight": 1.0
    },
    {
      "task_number": 296,
      "predicted_probs": [
        0.4663032591342926,
        0.36362263560295105,
        0.17007409036159515
      ],
      "predicted_class": "genuine",
      "true_soft_label": [
        0.0,
        0.0,
        1.0
      ],
      "true_top_class": "masking",
      "weight": 1.0
    },
    {
      "task_number": 314,
      "predicted_probs": [
        0.45925799012184143,
        0.3651423752307892,
        0.1755995899438858
      ],
      "predicted_class": "genuine",
      "true_soft_label": [
        0.0,
        1.0,
        0.0
      ],
      "true_top_class": "polite",
      "weight": 1.0
    },
    {
      "task_number": 355,
      "predicted_probs": [
        0.4641079306602478,
        0.365888386964798,
        0.17000368237495422
      ],
      "predicted_class": "genuine",
      "true_soft_label": [
        0.0,
        1.0,
        0.0
      ],
      "true_top_class": "polite",
      "weight": 1.0
    },
    {
      "task_number": 364,
      "predicted_probs": [
        0.463588148355484,
        0.36175140738487244,
        0.17466050386428833
      ],
      "predicted_class": "genuine",
      "true_soft_label": [
        0.0,
        1.0,
        0.0
      ],
      "true_top_class": "polite",
      "weight": 1.0
    },
    {
      "task_number": 374,
      "predicted_probs": [
        0.4525066316127777,
        0.37043750286102295,
        0.17705580592155457
      ],
      "predicted_class": "genuine",
      "true_soft_label": [
        1.0,
        0.0,
        0.0
      ],
      "true_top_class": "genuine",
      "weight": 1.0
    },
    {
      "task_number": 21,
      "predicted_probs": [
        0.4551059901714325,
        0.3897673785686493,
        0.1551266759634018
      ],
      "predicted_class": "genuine",
      "true_soft_label": [
        0.6000000238418579,
        0.4000000059604645,
        0.0
      ],
      "true_top_class": "genuine",
      "weight": 1.0
    },
    {
      "task_number": 28,
      "predicted_probs": [
        0.45035186409950256,
        0.38045811653137207,
        0.16918998956680298
      ],
      "predicted_class": "genuine",
      "true_soft_label": [
        0.6000000238418579,
        0.4000000059604645,
        0.0
      ],
      "true_top_class": "genuine",
      "weight": 1.0
    },
    {
      "task_number": 42,
      "predicted_probs": [
        0.4384191334247589,
        0.38852566480636597,
        0.17305518686771393
      ],
      "predicted_class": "genuine",
      "true_soft_label": [
        0.0,
        1.0,
        0.0
      ],
      "true_top_class": "polite",
      "weight": 1.0
    },
    {
      "task_number": 59,
      "predicted_probs": [
        0.438538521528244,
        0.389652281999588,
        0.17180919647216797
      ],
      "predicted_class": "genuine",
      "true_soft_label": [
        0.6666666865348816,
        0.3333333432674408,
        0.0
      ],
      "true_top_class": "genuine",
      "weight": 1.0
    },
    {
      "task_number": 71,
      "predicted_probs": [
        0.45776891708374023,
        0.3837890625,
        0.15844208002090454
      ],
      "predicted_class": "genuine",
      "true_soft_label": [
        0.0,
        0.0,
        1.0
      ],
      "true_top_class": "masking",
      "weight": 0.3333333333333333
    },
    {
      "task_number": 72,
      "predicted_probs": [
        0.4537222385406494,
        0.38953593373298645,
        0.1567419171333313
      ],
      "predicted_class": "genuine",
      "true_soft_label": [
        1.0,
        0.0,
        0.0
      ],
      "true_top_class": "genuine",
      "weight": 1.0
    },
    {
      "task_number": 81,
      "predicted_probs": [
        0.44971612095832825,
        0.387786328792572,
        0.1624975949525833
      ],
      "predicted_class": "genuine",
      "true_soft_label": [
        0.5,
        0.5,
        0.0
      ],
      "true_top_class": "genuine",
      "weight": 1.0
    },
    {
      "task_number": 83,
      "predicted_probs": [
        0.4485683739185333,
        0.38589051365852356,
        0.1655411422252655
      ],
      "predicted_class": "genuine",
      "true_soft_label": [
        0.0,
        0.5,
        0.5
      ],
      "true_top_class": "polite",
      "weight": 1.0
    },
    {
      "task_number": 102,
      "predicted_probs": [
        0.42843350768089294,
        0.3904247581958771,
        0.1811417192220688
      ],
      "predicted_class": "genuine",
      "true_soft_label": [
        1.0,
        0.0,
        0.0
      ],
      "true_top_class": "genuine",
      "weight": 1.0
    },
    {
      "task_number": 106,
      "predicted_probs": [
        0.43900346755981445,
        0.3911242187023163,
        0.16987234354019165
      ],
      "predicted_class": "genuine",
      "true_soft_label": [
        0.0,
        0.0,
        1.0
      ],
      "true_top_class": "masking",
      "weight": 1.0
    },
    {
      "task_number": 141,
      "predicted_probs": [
        0.4493321180343628,
        0.3880537152290344,
        0.16261419653892517
      ],
      "predicted_class": "genuine",
      "true_soft_label": [
        0.0,
        1.0,
        0.0
      ],
      "true_top_class": "polite",
      "weight": 1.0
    },
    {
      "task_number": 144,
      "predicted_probs": [
        0.4572896957397461,
        0.3820688724517822,
        0.16064149141311646
      ],
      "predicted_class": "genuine",
      "true_soft_label": [
        0.0,
        0.0,
        1.0
      ],
      "true_top_class": "masking",
      "weight": 1.0
    },
    {
      "task_number": 171,
      "predicted_probs": [
        0.4376193881034851,
        0.394146203994751,
        0.1682344377040863
      ],
      "predicted_class": "genuine",
      "true_soft_label": [
        0.0,
        1.0,
        0.0
      ],
      "true_top_class": "polite",
      "weight": 1.0
    },
    {
      "task_number": 177,
      "predicted_probs": [
        0.43247509002685547,
        0.38477063179016113,
        0.18275420367717743
      ],
      "predicted_class": "genuine",
      "true_soft_label": [
        1.0,
        0.0,
        0.0
      ],
      "true_top_class": "genuine",
      "weight": 1.0
    },
    {
      "task_number": 210,
      "predicted_probs": [
        0.45757076144218445,
        0.3834737539291382,
        0.15895546972751617
      ],
      "predicted_class": "genuine",
      "true_soft_label": [
        1.0,
        0.0,
        0.0
      ],
      "true_top_class": "genuine",
      "weight": 1.0
    },
    {
      "task_number": 221,
      "predicted_probs": [
        0.4423418641090393,
        0.39129266142845154,
        0.16636556386947632
      ],
      "predicted_class": "genuine",
      "true_soft_label": [
        0.0,
        0.0,
        1.0
      ],
      "true_top_class": "masking",
      "weight": 1.0
    },
    {
      "task_number": 256,
      "predicted_probs": [
        0.4341215193271637,
        0.39236393570899963,
        0.17351454496383667
      ],
      "predicted_class": "genuine",
      "true_soft_label": [
        1.0,
        0.0,
        0.0
      ],
      "true_top_class": "genuine",
      "weight": 1.0
    },
    {
      "task_number": 258,
      "predicted_probs": [
        0.4328776001930237,
        0.39384910464286804,
        0.17327328026294708
      ],
      "predicted_class": "genuine",
      "true_soft_label": [
        1.0,
        0.0,
        0.0
      ],
      "true_top_class": "genuine",
      "weight": 1.0
    },
    {
      "task_number": 266,
      "predicted_probs": [
        0.4491247236728668,
        0.39038920402526855,
        0.16048602759838104
      ],
      "predicted_class": "genuine",
      "true_soft_label": [
        0.0,
        0.0,
        1.0
      ],
      "true_top_class": "masking",
      "weight": 1.0
    },
    {
      "task_number": 273,
      "predicted_probs": [
        0.45537590980529785,
        0.38445544242858887,
        0.16016869246959686
      ],
      "predicted_class": "genuine",
      "true_soft_label": [
        0.0,
        1.0,
        0.0
      ],
      "true_top_class": "polite",
      "weight": 1.0
    },
    {
      "task_number": 277,
      "predicted_probs": [
        0.4077560603618622,
        0.3801615536212921,
        0.2120823860168457
      ],
      "predicted_class": "genuine",
      "true_soft_label": [
        0.0,
        1.0,
        0.0
      ],
      "true_top_class": "polite",
      "weight": 1.0
    },
    {
      "task_number": 301,
      "predicted_probs": [
        0.46217095851898193,
        0.38204365968704224,
        0.15578535199165344
      ],
      "predicted_class": "genuine",
      "true_soft_label": [
        0.0,
        1.0,
        0.0
      ],
      "true_top_class": "polite",
      "weight": 1.0
    },
    {
      "task_number": 313,
      "predicted_probs": [
        0.4541659653186798,
        0.3883536159992218,
        0.1574804186820984
      ],
      "predicted_class": "genuine",
      "true_soft_label": [
        1.0,
        0.0,
        0.0
      ],
      "true_top_class": "genuine",
      "weight": 1.0
    },
    {
      "task_number": 328,
      "predicted_probs": [
        0.4474610686302185,
        0.39009734988212585,
        0.16244153678417206
      ],
      "predicted_class": "genuine",
      "true_soft_label": [
        1.0,
        0.0,
        0.0
      ],
      "true_top_class": "genuine",
      "weight": 1.0
    },
    {
      "task_number": 356,
      "predicted_probs": [
        0.4426533579826355,
        0.3900361955165863,
        0.1673104465007782
      ],
      "predicted_class": "genuine",
      "true_soft_label": [
        0.0,
        0.0,
        1.0
      ],
      "true_top_class": "masking",
      "weight": 1.0
    },
    {
      "task_number": 357,
      "predicted_probs": [
        0.4474579095840454,
        0.3849336802959442,
        0.16760842502117157
      ],
      "predicted_class": "genuine",
      "true_soft_label": [
        1.0,
        0.0,
        0.0
      ],
      "true_top_class": "genuine",
      "weight": 1.0
    },
    {
      "task_number": 396,
      "predicted_probs": [
        0.4537253677845001,
        0.39041197299957275,
        0.15586262941360474
      ],
      "predicted_class": "genuine",
      "true_soft_label": [
        1.0,
        0.0,
        0.0
      ],
      "true_top_class": "genuine",
      "weight": 1.0
    },
    {
      "task_number": 3,
      "predicted_probs": [
        0.44157829880714417,
        0.38895729184150696,
        0.1694643795490265
      ],
      "predicted_class": "genuine",
      "true_soft_label": [
        0.800000011920929,
        0.20000000298023224,
        0.0
      ],
      "true_top_class": "genuine",
      "weight": 1.0
    },
    {
      "task_number": 6,
      "predicted_probs": [
        0.44179075956344604,
        0.3881738781929016,
        0.17003540694713593
      ],
      "predicted_class": "genuine",
      "true_soft_label": [
        0.4000000059604645,
        0.4000000059604645,
        0.20000000298023224
      ],
      "true_top_class": "genuine",
      "weight": 1.0
    },
    {
      "task_number": 32,
      "predicted_probs": [
        0.45196497440338135,
        0.38333001732826233,
        0.1647050678730011
      ],
      "predicted_class": "genuine",
      "true_soft_label": [
        0.5,
        0.5,
        0.0
      ],
      "true_top_class": "genuine",
      "weight": 0.5
    },
    {
      "task_number": 60,
      "predicted_probs": [
        0.43904751539230347,
        0.3841366767883301,
        0.17681576311588287
      ],
      "predicted_class": "genuine",
      "true_soft_label": [
        1.0,
        0.0,
        0.0
      ],
      "true_top_class": "genuine",
      "weight": 1.0
    },
    {
      "task_number": 73,
      "predicted_probs": [
        0.447929710149765,
        0.3843788206577301,
        0.16769152879714966
      ],
      "predicted_class": "genuine",
      "true_soft_label": [
        0.0,
        1.0,
        0.0
      ],
      "true_top_class": "polite",
      "weight": 1.0
    },
    {
      "task_number": 78,
      "predicted_probs": [
        0.4345712661743164,
        0.3848443627357483,
        0.18058443069458008
      ],
      "predicted_class": "genuine",
      "true_soft_label": [
        0.5,
        0.5,
        0.0
      ],
      "true_top_class": "genuine",
      "weight": 1.0
    },
    {
      "task_number": 80,
      "predicted_probs": [
        0.44426512718200684,
        0.38338810205459595,
        0.17234671115875244
      ],
      "predicted_class": "genuine",
      "true_soft_label": [
        1.0,
        0.0,
        0.0
      ],
      "true_top_class": "genuine",
      "weight": 1.0
    },
    {
      "task_number": 82,
      "predicted_probs": [
        0.4491978883743286,
        0.38455531001091003,
        0.16624681651592255
      ],
      "predicted_class": "genuine",
      "true_soft_label": [
        0.5,
        0.0,
        0.5
      ],
      "true_top_class": "genuine",
      "weight": 1.0
    },
    {
      "task_number": 120,
      "predicted_probs": [
        0.4443109333515167,
        0.38368096947669983,
        0.17200814187526703
      ],
      "predicted_class": "genuine",
      "true_soft_label": [
        0.0,
        1.0,
        0.0
      ],
      "true_top_class": "polite",
      "weight": 1.0
    },
    {
      "task_number": 139,
      "predicted_probs": [
        0.4431215822696686,
        0.3882560431957245,
        0.16862234473228455
      ],
      "predicted_class": "genuine",
      "true_soft_label": [
        0.0,
        0.0,
        1.0
      ],
      "true_top_class": "masking",
      "weight": 1.0
    },
    {
      "task_number": 167,
      "predicted_probs": [
        0.44100841879844666,
        0.3884662091732025,
        0.170525461435318
      ],
      "predicted_class": "genuine",
      "true_soft_label": [
        0.0,
        1.0,
        0.0
      ],
      "true_top_class": "polite",
      "weight": 1.0
    },
    {
      "task_number": 168,
      "predicted_probs": [
        0.4441424310207367,
        0.3823050260543823,
        0.17355257272720337
      ],
      "predicted_class": "genuine",
      "true_soft_label": [
        0.0,
        0.0,
        1.0
      ],
      "true_top_class": "masking",
      "weight": 1.0
    },
    {
      "task_number": 182,
      "predicted_probs": [
        0.4173898696899414,
        0.37954413890838623,
        0.20306603610515594
      ],
      "predicted_class": "genuine",
      "true_soft_label": [
        0.0,
        1.0,
        0.0
      ],
      "true_top_class": "polite",
      "weight": 1.0
    },
    {
      "task_number": 196,
      "predicted_probs": [
        0.4490600526332855,
        0.3857576251029968,
        0.16518232226371765
      ],
      "predicted_class": "genuine",
      "true_soft_label": [
        1.0,
        0.0,
        0.0
      ],
      "true_top_class": "genuine",
      "weight": 1.0
    },
    {
      "task_number": 201,
      "predicted_probs": [
        0.4486703872680664,
        0.3854431211948395,
        0.16588644683361053
      ],
      "predicted_class": "genuine",
      "true_soft_label": [
        1.0,
        0.0,
        0.0
      ],
      "true_top_class": "genuine",
      "weight": 1.0
    },
    {
      "task_number": 203,
      "predicted_probs": [
        0.4478459656238556,
        0.38674303889274597,
        0.16541104018688202
      ],
      "predicted_class": "genuine",
      "true_soft_label": [
        1.0,
        0.0,
        0.0
      ],
      "true_top_class": "genuine",
      "weight": 1.0
    },
    {
      "task_number": 232,
      "predicted_probs": [
        0.45102396607398987,
        0.38762298226356506,
        0.16135309636592865
      ],
      "predicted_class": "genuine",
      "true_soft_label": [
        1.0,
        0.0,
        0.0
      ],
      "true_top_class": "genuine",
      "weight": 1.0
    },
    {
      "task_number": 234,
      "predicted_probs": [
        0.4419936537742615,
        0.38537052273750305,
        0.17263585329055786
      ],
      "predicted_class": "genuine",
      "true_soft_label": [
        0.0,
        1.0,
        0.0
      ],
      "true_top_class": "polite",
      "weight": 1.0
    },
    {
      "task_number": 245,
      "predicted_probs": [
        0.4364301860332489,
        0.3868117332458496,
        0.1767580658197403
      ],
      "predicted_class": "genuine",
      "true_soft_label": [
        0.0,
        0.0,
        1.0
      ],
      "true_top_class": "masking",
      "weight": 1.0
    },
    {
      "task_number": 262,
      "predicted_probs": [
        0.4356938600540161,
        0.38402315974235535,
        0.18028299510478973
      ],
      "predicted_class": "genuine",
      "true_soft_label": [
        0.0,
        1.0,
        0.0
      ],
      "true_top_class": "polite",
      "weight": 1.0
    },
    {
      "task_number": 265,
      "predicted_probs": [
        0.4398103356361389,
        0.38779008388519287,
        0.1723996102809906
      ],
      "predicted_class": "genuine",
      "true_soft_label": [
        1.0,
        0.0,
        0.0
      ],
      "true_top_class": "genuine",
      "weight": 1.0
    },
    {
      "task_number": 282,
      "predicted_probs": [
        0.44264519214630127,
        0.3830854594707489,
        0.17426936328411102
      ],
      "predicted_class": "genuine",
      "true_soft_label": [
        1.0,
        0.0,
        0.0
      ],
      "true_top_class": "genuine",
      "weight": 1.0
    },
    {
      "task_number": 287,
      "predicted_probs": [
        0.4241223931312561,
        0.38161057233810425,
        0.19426707923412323
      ],
      "predicted_class": "genuine",
      "true_soft_label": [
        1.0,
        0.0,
        0.0
      ],
      "true_top_class": "genuine",
      "weight": 1.0
    },
    {
      "task_number": 288,
      "predicted_probs": [
        0.4222090542316437,
        0.3862540125846863,
        0.19153697788715363
      ],
      "predicted_class": "genuine",
      "true_soft_label": [
        0.0,
        1.0,
        0.0
      ],
      "true_top_class": "polite",
      "weight": 1.0
    },
    {
      "task_number": 304,
      "predicted_probs": [
        0.4492889642715454,
        0.38301584124565125,
        0.16769514977931976
      ],
      "predicted_class": "genuine",
      "true_soft_label": [
        1.0,
        0.0,
        0.0
      ],
      "true_top_class": "genuine",
      "weight": 1.0
    },
    {
      "task_number": 316,
      "predicted_probs": [
        0.4407964050769806,
        0.384015828371048,
        0.17518772184848785
      ],
      "predicted_class": "genuine",
      "true_soft_label": [
        1.0,
        0.0,
        0.0
      ],
      "true_top_class": "genuine",
      "weight": 1.0
    },
    {
      "task_number": 376,
      "predicted_probs": [
        0.4367714524269104,
        0.38422051072120667,
        0.17900799214839935
      ],
      "predicted_class": "genuine",
      "true_soft_label": [
        1.0,
        0.0,
        0.0
      ],
      "true_top_class": "genuine",
      "weight": 1.0
    },
    {
      "task_number": 15,
      "predicted_probs": [
        0.433733195066452,
        0.3981530964374542,
        0.16811372339725494
      ],
      "predicted_class": "genuine",
      "true_soft_label": [
        0.0,
        0.5,
        0.5
      ],
      "true_top_class": "polite",
      "weight": 0.4
    },
    {
      "task_number": 25,
      "predicted_probs": [
        0.4457239806652069,
        0.3920677602291107,
        0.16220830380916595
      ],
      "predicted_class": "genuine",
      "true_soft_label": [
        1.0,
        0.0,
        0.0
      ],
      "true_top_class": "genuine",
      "weight": 1.0
    },
    {
      "task_number": 31,
      "predicted_probs": [
        0.452114075422287,
        0.38697534799575806,
        0.16091056168079376
      ],
      "predicted_class": "genuine",
      "true_soft_label": [
        0.6666666865348816,
        0.3333333432674408,
        0.0
      ],
      "true_top_class": "genuine",
      "weight": 0.6
    },
    {
      "task_number": 34,
      "predicted_probs": [
        0.45136764645576477,
        0.3894942104816437,
        0.15913820266723633
      ],
      "predicted_class": "genuine",
      "true_soft_label": [
        0.5,
        0.5,
        0.0
      ],
      "true_top_class": "genuine",
      "weight": 0.5
    },
    {
      "task_number": 38,
      "predicted_probs": [
        0.45865553617477417,
        0.38283610343933105,
        0.15850837528705597
      ],
      "predicted_class": "genuine",
      "true_soft_label": [
        0.5,
        0.5,
        0.0
      ],
      "true_top_class": "genuine",
      "weight": 1.0
    },
    {
      "task_number": 45,
      "predicted_probs": [
        0.4390275776386261,
        0.3948872685432434,
        0.1660851687192917
      ],
      "predicted_class": "genuine",
      "true_soft_label": [
        0.6666666865348816,
        0.3333333432674408,
        0.0
      ],
      "true_top_class": "genuine",
      "weight": 1.0
    },
    {
      "task_number": 46,
      "predicted_probs": [
        0.41670310497283936,
        0.39460983872413635,
        0.1886870563030243
      ],
      "predicted_class": "genuine",
      "true_soft_label": [
        0.3333333432674408,
        0.6666666865348816,
        0.0
      ],
      "true_top_class": "polite",
      "weight": 1.0
    },
    {
      "task_number": 55,
      "predicted_probs": [
        0.44363081455230713,
        0.38359731435775757,
        0.17277181148529053
      ],
      "predicted_class": "genuine",
      "true_soft_label": [
        0.0,
        1.0,
        0.0
      ],
      "true_top_class": "polite",
      "weight": 0.3333333333333333
    },
    {
      "task_number": 69,
      "predicted_probs": [
        0.4431430697441101,
        0.39360859990119934,
        0.16324830055236816
      ],
      "predicted_class": "genuine",
      "true_soft_label": [
        0.0,
        0.5,
        0.5
      ],
      "true_top_class": "polite",
      "weight": 0.6666666666666666
    },
    {
      "task_number": 101,
      "predicted_probs": [
        0.440726101398468,
        0.3937259912490845,
        0.1655479520559311
      ],
      "predicted_class": "genuine",
      "true_soft_label": [
        1.0,
        0.0,
        0.0
      ],
      "true_top_class": "genuine",
      "weight": 1.0
    },
    {
      "task_number": 110,
      "predicted_probs": [
        0.44355735182762146,
        0.393376886844635,
        0.1630658060312271
      ],
      "predicted_class": "genuine",
      "true_soft_label": [
        0.0,
        0.0,
        1.0
      ],
      "true_top_class": "masking",
      "weight": 1.0
    },
    {
      "task_number": 114,
      "predicted_probs": [
        0.45112600922584534,
        0.38357049226760864,
        0.16530345380306244
      ],
      "predicted_class": "genuine",
      "true_soft_label": [
        0.0,
        1.0,
        0.0
      ],
      "true_top_class": "polite",
      "weight": 1.0
    },
    {
      "task_number": 135,
      "predicted_probs": [
        0.43893375992774963,
        0.38510632514953613,
        0.17595990002155304
      ],
      "predicted_class": "genuine",
      "true_soft_label": [
        1.0,
        0.0,
        0.0
      ],
      "true_top_class": "genuine",
      "weight": 1.0
    },
    {
      "task_number": 198,
      "predicted_probs": [
        0.45136889815330505,
        0.39260876178741455,
        0.15602236986160278
      ],
      "predicted_class": "genuine",
      "true_soft_label": [
        1.0,
        0.0,
        0.0
      ],
      "true_top_class": "genuine",
      "weight": 1.0
    },
    {
      "task_number": 199,
      "predicted_probs": [
        0.4430800974369049,
        0.39534297585487366,
        0.16157686710357666
      ],
      "predicted_class": "genuine",
      "true_soft_label": [
        1.0,
        0.0,
        0.0
      ],
      "true_top_class": "genuine",
      "weight": 1.0
    },
    {
      "task_number": 204,
      "predicted_probs": [
        0.44323140382766724,
        0.3924431800842285,
        0.16432543098926544
      ],
      "predicted_class": "genuine",
      "true_soft_label": [
        0.0,
        0.0,
        1.0
      ],
      "true_top_class": "masking",
      "weight": 1.0
    },
    {
      "task_number": 220,
      "predicted_probs": [
        0.43658772110939026,
        0.39591118693351746,
        0.16750109195709229
      ],
      "predicted_class": "genuine",
      "true_soft_label": [
        0.0,
        0.0,
        1.0
      ],
      "true_top_class": "masking",
      "weight": 1.0
    },
    {
      "task_number": 243,
      "predicted_probs": [
        0.43322014808654785,
        0.39433979988098145,
        0.1724400818347931
      ],
      "predicted_class": "genuine",
      "true_soft_label": [
        1.0,
        0.0,
        0.0
      ],
      "true_top_class": "genuine",
      "weight": 1.0
    },
    {
      "task_number": 264,
      "predicted_probs": [
        0.45297858119010925,
        0.3885659873485565,
        0.15845544636249542
      ],
      "predicted_class": "genuine",
      "true_soft_label": [
        0.0,
        0.0,
        1.0
      ],
      "true_top_class": "masking",
      "weight": 1.0
    },
    {
      "task_number": 280,
      "predicted_probs": [
        0.4495396316051483,
        0.38440772891044617,
        0.16605263948440552
      ],
      "predicted_class": "genuine",
      "true_soft_label": [
        1.0,
        0.0,
        0.0
      ],
      "true_top_class": "genuine",
      "weight": 1.0
    },
    {
      "task_number": 291,
      "predicted_probs": [
        0.4275306463241577,
        0.3991367816925049,
        0.17333251237869263
      ],
      "predicted_class": "genuine",
      "true_soft_label": [
        0.0,
        1.0,
        0.0
      ],
      "true_top_class": "polite",
      "weight": 1.0
    },
    {
      "task_number": 300,
      "predicted_probs": [
        0.4587578773498535,
        0.38220155239105225,
        0.15904061496257782
      ],
      "predicted_class": "genuine",
      "true_soft_label": [
        0.0,
        1.0,
        0.0
      ],
      "true_top_class": "polite",
      "weight": 1.0
    },
    {
      "task_number": 331,
      "predicted_probs": [
        0.44254598021507263,
        0.38783183693885803,
        0.16962212324142456
      ],
      "predicted_class": "genuine",
      "true_soft_label": [
        1.0,
        0.0,
        0.0
      ],
      "true_top_class": "genuine",
      "weight": 1.0
    },
    {
      "task_number": 354,
      "predicted_probs": [
        0.4379383623600006,
        0.39400339126586914,
        0.16805824637413025
      ],
      "predicted_class": "genuine",
      "true_soft_label": [
        0.0,
        0.0,
        1.0
      ],
      "true_top_class": "masking",
      "weight": 1.0
    },
    {
      "task_number": 359,
      "predicted_probs": [
        0.4489847421646118,
        0.3942524194717407,
        0.15676283836364746
      ],
      "predicted_class": "genuine",
      "true_soft_label": [
        1.0,
        0.0,
        0.0
      ],
      "true_top_class": "genuine",
      "weight": 1.0
    },
    {
      "task_number": 362,
      "predicted_probs": [
        0.4297800064086914,
        0.3928678035736084,
        0.17735211551189423
      ],
      "predicted_class": "genuine",
      "true_soft_label": [
        0.0,
        1.0,
        0.0
      ],
      "true_top_class": "polite",
      "weight": 1.0
    },
    {
      "task_number": 394,
      "predicted_probs": [
        0.4350437819957733,
        0.39650973677635193,
        0.16844646632671356
      ],
      "predicted_class": "genuine",
      "true_soft_label": [
        1.0,
        0.0,
        0.0
      ],
      "true_top_class": "genuine",
      "weight": 1.0
    },
    {
      "task_number": 1,
      "predicted_probs": [
        0.45668497681617737,
        0.3752191364765167,
        0.1680958867073059
      ],
      "predicted_class": "genuine",
      "true_soft_label": [
        0.800000011920929,
        0.20000000298023224,
        0.0
      ],
      "true_top_class": "genuine",
      "weight": 1.0
    },
    {
      "task_number": 5,
      "predicted_probs": [
        0.43701037764549255,
        0.3871574103832245,
        0.17583227157592773
      ],
      "predicted_class": "genuine",
      "true_soft_label": [
        0.4000000059604645,
        0.20000000298023224,
        0.4000000059604645
      ],
      "true_top_class": "genuine",
      "weight": 1.0
    },
    {
      "task_number": 13,
      "predicted_probs": [
        0.46343177556991577,
        0.3703342080116272,
        0.166234090924263
      ],
      "predicted_class": "genuine",
      "true_soft_label": [
        0.0,
        0.5,
        0.5
      ],
      "true_top_class": "polite",
      "weight": 0.4
    },
    {
      "task_number": 29,
      "predicted_probs": [
        0.45528456568717957,
        0.37098774313926697,
        0.17372772097587585
      ],
      "predicted_class": "genuine",
      "true_soft_label": [
        0.0,
        1.0,
        0.0
      ],
      "true_top_class": "polite",
      "weight": 0.4
    },
    {
      "task_number": 30,
      "predicted_probs": [
        0.44496649503707886,
        0.38122260570526123,
        0.1738109439611435
      ],
      "predicted_class": "genuine",
      "true_soft_label": [
        0.4000000059604645,
        0.6000000238418579,
        0.0
      ],
      "true_top_class": "polite",
      "weight": 1.0
    },
    {
      "task_number": 35,
      "predicted_probs": [
        0.47392183542251587,
        0.367211252450943,
        0.15886691212654114
      ],
      "predicted_class": "genuine",
      "true_soft_label": [
        0.3333333432674408,
        0.6666666865348816,
        0.0
      ],
      "true_top_class": "polite",
      "weight": 0.75
    },
    {
      "task_number": 39,
      "predicted_probs": [
        0.45510828495025635,
        0.37235674262046814,
        0.17253495752811432
      ],
      "predicted_class": "genuine",
      "true_soft_label": [
        0.0,
        0.25,
        0.75
      ],
      "true_top_class": "masking",
      "weight": 1.0
    },
    {
      "task_number": 65,
      "predicted_probs": [
        0.4679572284221649,
        0.36679965257644653,
        0.16524313390254974
      ],
      "predicted_class": "genuine",
      "true_soft_label": [
        0.3333333432674408,
        0.0,
        0.6666666865348816
      ],
      "true_top_class": "masking",
      "weight": 1.0
    },
    {
      "task_number": 66,
      "predicted_probs": [
        0.46058860421180725,
        0.37148693203926086,
        0.1679244488477707
      ],
      "predicted_class": "genuine",
      "true_soft_label": [
        0.0,
        0.0,
        1.0
      ],
      "true_top_class": "masking",
      "weight": 1.0
    },
    {
      "task_number": 122,
      "predicted_probs": [
        0.45837169885635376,
        0.37180784344673157,
        0.16982048749923706
      ],
      "predicted_class": "genuine",
      "true_soft_label": [
        0.0,
        1.0,
        0.0
      ],
      "true_top_class": "polite",
      "weight": 1.0
    },
    {
      "task_number": 124,
      "predicted_probs": [
        0.4617120027542114,
        0.37442466616630554,
        0.16386333107948303
      ],
      "predicted_class": "genuine",
      "true_soft_label": [
        0.0,
        1.0,
        0.0
      ],
      "true_top_class": "polite",
      "weight": 1.0
    },
    {
      "task_number": 160,
      "predicted_probs": [
        0.4656802713871002,
        0.3694334328174591,
        0.16488631069660187
      ],
      "predicted_class": "genuine",
      "true_soft_label": [
        1.0,
        0.0,
        0.0
      ],
      "true_top_class": "genuine",
      "weight": 1.0
    },
    {
      "task_number": 181,
      "predicted_probs": [
        0.426674485206604,
        0.37923693656921387,
        0.19408860802650452
      ],
      "predicted_class": "genuine",
      "true_soft_label": [
        1.0,
        0.0,
        0.0
      ],
      "true_top_class": "genuine",
      "weight": 1.0
    },
    {
      "task_number": 187,
      "predicted_probs": [
        0.45916682481765747,
        0.36807283759117126,
        0.17276029288768768
      ],
      "predicted_class": "genuine",
      "true_soft_label": [
        0.0,
        1.0,
        0.0
      ],
      "true_top_class": "polite",
      "weight": 1.0
    },
    {
      "task_number": 216,
      "predicted_probs": [
        0.46219590306282043,
        0.3687290549278259,
        0.16907502710819244
      ],
      "predicted_class": "genuine",
      "true_soft_label": [
        1.0,
        0.0,
        0.0
      ],
      "true_top_class": "genuine",
      "weight": 1.0
    },
    {
      "task_number": 226,
      "predicted_probs": [
        0.45939263701438904,
        0.37384113669395447,
        0.16676625609397888
      ],
      "predicted_class": "genuine",
      "true_soft_label": [
        1.0,
        0.0,
        0.0
      ],
      "true_top_class": "genuine",
      "weight": 1.0
    },
    {
      "task_number": 238,
      "predicted_probs": [
        0.45861902832984924,
        0.37316399812698364,
        0.1682170331478119
      ],
      "predicted_class": "genuine",
      "true_soft_label": [
        0.0,
        1.0,
        0.0
      ],
      "true_top_class": "polite",
      "weight": 1.0
    },
    {
      "task_number": 240,
      "predicted_probs": [
        0.4519258439540863,
        0.37731701135635376,
        0.17075711488723755
      ],
      "predicted_class": "genuine",
      "true_soft_label": [
        0.0,
        1.0,
        0.0
      ],
      "true_top_class": "polite",
      "weight": 1.0
    },
    {
      "task_number": 261,
      "predicted_probs": [
        0.4420601725578308,
        0.3793434798717499,
        0.1785963922739029
      ],
      "predicted_class": "genuine",
      "true_soft_label": [
        0.0,
        1.0,
        0.0
      ],
      "true_top_class": "polite",
      "weight": 1.0
    },
    {
      "task_number": 275,
      "predicted_probs": [
        0.43843331933021545,
        0.3827333152294159,
        0.17883333563804626
      ],
      "predicted_class": "genuine",
      "true_soft_label": [
        1.0,
        0.0,
        0.0
      ],
      "true_top_class": "genuine",
      "weight": 1.0
    },
    {
      "task_number": 278,
      "predicted_probs": [
        0.4135545492172241,
        0.37964537739753723,
        0.20680014789104462
      ],
      "predicted_class": "genuine",
      "true_soft_label": [
        0.0,
        1.0,
        0.0
      ],
      "true_top_class": "polite",
      "weight": 1.0
    },
    {
      "task_number": 283,
      "predicted_probs": [
        0.4596620500087738,
        0.37131986021995544,
        0.16901808977127075
      ],
      "predicted_class": "genuine",
      "true_soft_label": [
        1.0,
        0.0,
        0.0
      ],
      "true_top_class": "genuine",
      "weight": 1.0
    },
    {
      "task_number": 311,
      "predicted_probs": [
        0.46356263756752014,
        0.3706398010253906,
        0.16579759120941162
      ],
      "predicted_class": "genuine",
      "true_soft_label": [
        1.0,
        0.0,
        0.0
      ],
      "true_top_class": "genuine",
      "weight": 1.0
    },
    {
      "task_number": 330,
      "predicted_probs": [
        0.4607000946998596,
        0.3718114197254181,
        0.16748842597007751
      ],
      "predicted_class": "genuine",
      "true_soft_label": [
        0.0,
        1.0,
        0.0
      ],
      "true_top_class": "polite",
      "weight": 1.0
    },
    {
      "task_number": 365,
      "predicted_probs": [
        0.4432387948036194,
        0.3783271908760071,
        0.17843395471572876
      ],
      "predicted_class": "genuine",
      "true_soft_label": [
        1.0,
        0.0,
        0.0
      ],
      "true_top_class": "genuine",
      "weight": 1.0
    },
    {
      "task_number": 391,
      "predicted_probs": [
        0.4560391306877136,
        0.3723936975002289,
        0.1715671420097351
      ],
      "predicted_class": "genuine",
      "true_soft_label": [
        0.0,
        1.0,
        0.0
      ],
      "true_top_class": "polite",
      "weight": 1.0
    },
    {
      "task_number": 395,
      "predicted_probs": [
        0.45443159341812134,
        0.37219685316085815,
        0.17337153851985931
      ],
      "predicted_class": "genuine",
      "true_soft_label": [
        0.0,
        0.0,
        1.0
      ],
      "true_top_class": "masking",
      "weight": 1.0
    },
    {
      "task_number": 4,
      "predicted_probs": [
        0.4511238932609558,
        0.37806132435798645,
        0.17081484198570251
      ],
      "predicted_class": "genuine",
      "true_soft_label": [
        0.6000000238418579,
        0.20000000298023224,
        0.20000000298023224
      ],
      "true_top_class": "genuine",
      "weight": 1.0
    },
    {
      "task_number": 26,
      "predicted_probs": [
        0.4393375813961029,
        0.38033992052078247,
        0.1803225427865982
      ],
      "predicted_class": "genuine",
      "true_soft_label": [
        0.20000000298023224,
        0.20000000298023224,
        0.6000000238418579
      ],
      "true_top_class": "masking",
      "weight": 1.0
    },
    {
      "task_number": 43,
      "predicted_probs": [
        0.4256729781627655,
        0.383864164352417,
        0.1904628574848175
      ],
      "predicted_class": "genuine",
      "true_soft_label": [
        0.3333333432674408,
        0.6666666865348816,
        0.0
      ],
      "true_top_class": "polite",
      "weight": 1.0
    },
    {
      "task_number": 44,
      "predicted_probs": [
        0.4276939630508423,
        0.38354432582855225,
        0.18876174092292786
      ],
      "predicted_class": "genuine",
      "true_soft_label": [
        0.5,
        0.5,
        0.0
      ],
      "true_top_class": "genuine",
      "weight": 0.6666666666666666
    },
    {
      "task_number": 47,
      "predicted_probs": [
        0.41785043478012085,
        0.3851172924041748,
        0.19703230261802673
      ],
      "predicted_class": "genuine",
      "true_soft_label": [
        1.0,
        0.0,
        0.0
      ],
      "true_top_class": "genuine",
      "weight": 0.6666666666666666
    },
    {
      "task_number": 48,
      "predicted_probs": [
        0.4170767664909363,
        0.38436079025268555,
        0.19856242835521698
      ],
      "predicted_class": "genuine",
      "true_soft_label": [
        0.6666666865348816,
        0.3333333432674408,
        0.0
      ],
      "true_top_class": "genuine",
      "weight": 1.0
    },
    {
      "task_number": 51,
      "predicted_probs": [
        0.4310988187789917,
        0.3816751539707184,
        0.18722599744796753
      ],
      "predicted_class": "genuine",
      "true_soft_label": [
        1.0,
        0.0,
        0.0
      ],
      "true_top_class": "genuine",
      "weight": 1.0
    },
    {
      "task_number": 68,
      "predicted_probs": [
        0.41995105147361755,
        0.38577812910079956,
        0.19427084922790527
      ],
      "predicted_class": "genuine",
      "true_soft_label": [
        0.0,
        1.0,
        0.0
      ],
      "true_top_class": "polite",
      "weight": 0.6666666666666666
    },
    {
      "task_number": 74,
      "predicted_probs": [
        0.4442201852798462,
        0.3826940655708313,
        0.17308573424816132
      ],
      "predicted_class": "genuine",
      "true_soft_label": [
        0.0,
        1.0,
        0.0
      ],
      "true_top_class": "polite",
      "weight": 1.0
    },
    {
      "task_number": 89,
      "predicted_probs": [
        0.4422595798969269,
        0.3824799954891205,
        0.17526043951511383
      ],
      "predicted_class": "genuine",
      "true_soft_label": [
        1.0,
        0.0,
        0.0
      ],
      "true_top_class": "genuine",
      "weight": 1.0
    },
    {
      "task_number": 111,
      "predicted_probs": [
        0.4372031092643738,
        0.3818650543689728,
        0.18093182146549225
      ],
      "predicted_class": "genuine",
      "true_soft_label": [
        0.0,
        1.0,
        0.0
      ],
      "true_top_class": "polite",
      "weight": 1.0
    },
    {
      "task_number": 162,
      "predicted_probs": [
        0.4367746412754059,
        0.3829575777053833,
        0.18026778101921082
      ],
      "predicted_class": "genuine",
      "true_soft_label": [
        1.0,
        0.0,
        0.0
      ],
      "true_top_class": "genuine",
      "weight": 1.0
    },
    {
      "task_number": 173,
      "predicted_probs": [
        0.4355619549751282,
        0.38382619619369507,
        0.18061187863349915
      ],
      "predicted_class": "genuine",
      "true_soft_label": [
        0.0,
        1.0,
        0.0
      ],
      "true_top_class": "polite",
      "weight": 1.0
    },
    {
      "task_number": 180,
      "predicted_probs": [
        0.42865169048309326,
        0.3860761821269989,
        0.18527212738990784
      ],
      "predicted_class": "genuine",
      "true_soft_label": [
        0.0,
        0.0,
        1.0
      ],
      "true_top_class": "masking",
      "weight": 1.0
    },
    {
      "task_number": 202,
      "predicted_probs": [
        0.45133402943611145,
        0.37652555108070374,
        0.17214037477970123
      ],
      "predicted_class": "genuine",
      "true_soft_label": [
        1.0,
        0.0,
        0.0
      ],
      "true_top_class": "genuine",
      "weight": 1.0
    },
    {
      "task_number": 213,
      "predicted_probs": [
        0.44155949354171753,
        0.3830883502960205,
        0.17535214126110077
      ],
      "predicted_class": "genuine",
      "true_soft_label": [
        1.0,
        0.0,
        0.0
      ],
      "true_top_class": "genuine",
      "weight": 1.0
    },
    {
      "task_number": 218,
      "predicted_probs": [
        0.44748616218566895,
        0.3784111738204956,
        0.17410260438919067
      ],
      "predicted_class": "genuine",
      "true_soft_label": [
        1.0,
        0.0,
        0.0
      ],
      "true_top_class": "genuine",
      "weight": 1.0
    },
    {
      "task_number": 225,
      "predicted_probs": [
        0.453471302986145,
        0.3765571415424347,
        0.1699715107679367
      ],
      "predicted_class": "genuine",
      "true_soft_label": [
        0.0,
        1.0,
        0.0
      ],
      "true_top_class": "polite",
      "weight": 1.0
    },
    {
      "task_number": 260,
      "predicted_probs": [
        0.4257480800151825,
        0.38770338892936707,
        0.18654859066009521
      ],
      "predicted_class": "genuine",
      "true_soft_label": [
        0.0,
        1.0,
        0.0
      ],
      "true_top_class": "polite",
      "weight": 1.0
    },
    {
      "task_number": 271,
      "predicted_probs": [
        0.44304847717285156,
        0.3835160732269287,
        0.1734354943037033
      ],
      "predicted_class": "genuine",
      "true_soft_label": [
        1.0,
        0.0,
        0.0
      ],
      "true_top_class": "genuine",
      "weight": 1.0
    },
    {
      "task_number": 286,
      "predicted_probs": [
        0.41487839818000793,
        0.3860052525997162,
        0.1991163194179535
      ],
      "predicted_class": "genuine",
      "true_soft_label": [
        0.0,
        1.0,
        0.0
      ],
      "true_top_class": "polite",
      "weight": 1.0
    },
    {
      "task_number": 290,
      "predicted_probs": [
        0.43416550755500793,
        0.3848423957824707,
        0.18099209666252136
      ],
      "predicted_class": "genuine",
      "true_soft_label": [
        1.0,
        0.0,
        0.0
      ],
      "true_top_class": "genuine",
      "weight": 1.0
    },
    {
      "task_number": 292,
      "predicted_probs": [
        0.43450331687927246,
        0.3833658993244171,
        0.18213070929050446
      ],
      "predicted_class": "genuine",
      "true_soft_label": [
        1.0,
        0.0,
        0.0
      ],
      "true_top_class": "genuine",
      "weight": 1.0
    },
    {
      "task_number": 295,
      "predicted_probs": [
        0.4474699795246124,
        0.37989023327827454,
        0.17263972759246826
      ],
      "predicted_class": "genuine",
      "true_soft_label": [
        1.0,
        0.0,
        0.0
      ],
      "true_top_class": "genuine",
      "weight": 1.0
    },
    {
      "task_number": 297,
      "predicted_probs": [
        0.43672606348991394,
        0.3819693624973297,
        0.18130463361740112
      ],
      "predicted_class": "genuine",
      "true_soft_label": [
        0.0,
        0.0,
        1.0
      ],
      "true_top_class": "masking",
      "weight": 1.0
    },
    {
      "task_number": 326,
      "predicted_probs": [
        0.44955286383628845,
        0.37618255615234375,
        0.17426452040672302
      ],
      "predicted_class": "genuine",
      "true_soft_label": [
        1.0,
        0.0,
        0.0
      ],
      "true_top_class": "genuine",
      "weight": 1.0
    },
    {
      "task_number": 367,
      "predicted_probs": [
        0.4258224070072174,
        0.38495150208473206,
        0.18922610580921173
      ],
      "predicted_class": "genuine",
      "true_soft_label": [
        0.0,
        1.0,
        0.0
      ],
      "true_top_class": "polite",
      "weight": 1.0
    },
    {
      "task_number": 8,
      "predicted_probs": [
        0.45988526940345764,
        0.3795004189014435,
        0.16061432659626007
      ],
      "predicted_class": "genuine",
      "true_soft_label": [
        0.0,
        1.0,
        0.0
      ],
      "true_top_class": "polite",
      "weight": 0.2
    },
    {
      "task_number": 10,
      "predicted_probs": [
        0.4570421278476715,
        0.3799545466899872,
        0.16300329566001892
      ],
      "predicted_class": "genuine",
      "true_soft_label": [
        0.800000011920929,
        0.0,
        0.20000000298023224
      ],
      "true_top_class": "genuine",
      "weight": 1.0
    },
    {
      "task_number": 16,
      "predicted_probs": [
        0.46121805906295776,
        0.37712544202804565,
        0.16165652871131897
      ],
      "predicted_class": "genuine",
      "true_soft_label": [
        1.0,
        0.0,
        0.0
      ],
      "true_top_class": "genuine",
      "weight": 1.0
    },
    {
      "task_number": 37,
      "predicted_probs": [
        0.4597596824169159,
        0.3787382245063782,
        0.16150209307670593
      ],
      "predicted_class": "genuine",
      "true_soft_label": [
        0.5,
        0.25,
        0.25
      ],
      "true_top_class": "genuine",
      "weight": 1.0
    },
    {
      "task_number": 53,
      "predicted_probs": [
        0.45945489406585693,
        0.3745743930339813,
        0.16597072780132294
      ],
      "predicted_class": "genuine",
      "true_soft_label": [
        0.0,
        1.0,
        0.0
      ],
      "true_top_class": "polite",
      "weight": 0.6666666666666666
    },
    {
      "task_number": 57,
      "predicted_probs": [
        0.4619504511356354,
        0.3764621317386627,
        0.1615874022245407
      ],
      "predicted_class": "genuine",
      "true_soft_label": [
        0.3333333432674408,
        0.3333333432674408,
        0.3333333432674408
      ],
      "true_top_class": "genuine",
      "weight": 1.0
    },
    {
      "task_number": 63,
      "predicted_probs": [
        0.4435712695121765,
        0.38476860523223877,
        0.17166006565093994
      ],
      "predicted_class": "genuine",
      "true_soft_label": [
        0.0,
        1.0,
        0.0
      ],
      "true_top_class": "polite",
      "weight": 1.0
    },
    {
      "task_number": 86,
      "predicted_probs": [
        0.4341845214366913,
        0.38716453313827515,
        0.17865100502967834
      ],
      "predicted_class": "genuine",
      "true_soft_label": [
        0.5,
        0.5,
        0.0
      ],
      "true_top_class": "genuine",
      "weight": 1.0
    },
    {
      "task_number": 91,
      "predicted_probs": [
        0.45030665397644043,
        0.3797675371170044,
        0.16992582380771637
      ],
      "predicted_class": "genuine",
      "true_soft_label": [
        0.0,
        0.5,
        0.5
      ],
      "true_top_class": "polite",
      "weight": 1.0
    },
    {
      "task_number": 105,
      "predicted_probs": [
        0.4395311772823334,
        0.38144204020500183,
        0.17902681231498718
      ],
      "predicted_class": "genuine",
      "true_soft_label": [
        0.0,
        0.0,
        1.0
      ],
      "true_top_class": "masking",
      "weight": 1.0
    },
    {
      "task_number": 107,
      "predicted_probs": [
        0.4642278850078583,
        0.3788226842880249,
        0.15694943070411682
      ],
      "predicted_class": "genuine",
      "true_soft_label": [
        0.0,
        1.0,
        0.0
      ],
      "true_top_class": "polite",
      "weight": 1.0
    },
    {
      "task_number": 130,
      "predicted_probs": [
        0.45341482758522034,
        0.37720683217048645,
        0.1693783849477768
      ],
      "predicted_class": "genuine",
      "true_soft_label": [
        1.0,
        0.0,
        0.0
      ],
      "true_top_class": "genuine",
      "weight": 1.0
    },
    {
      "task_number": 132,
      "predicted_probs": [
        0.44079312682151794,
        0.38002607226371765,
        0.17918077111244202
      ],
      "predicted_class": "genuine",
      "true_soft_label": [
        0.0,
        1.0,
        0.0
      ],
      "true_top_class": "polite",
      "weight": 1.0
    },
    {
      "task_number": 137,
      "predicted_probs": [
        0.4437495172023773,
        0.3835184574127197,
        0.17273207008838654
      ],
      "predicted_class": "genuine",
      "true_soft_label": [
        0.0,
        1.0,
        0.0
      ],
      "true_top_class": "polite",
      "weight": 1.0
    },
    {
      "task_number": 176,
      "predicted_probs": [
        0.4300130307674408,
        0.3827296793460846,
        0.18725727498531342
      ],
      "predicted_class": "genuine",
      "true_soft_label": [
        0.0,
        1.0,
        0.0
      ],
      "true_top_class": "polite",
      "weight": 1.0
    },
    {
      "task_number": 178,
      "predicted_probs": [
        0.4323813319206238,
        0.3854621946811676,
        0.18215647339820862
      ],
      "predicted_class": "genuine",
      "true_soft_label": [
        1.0,
        0.0,
        0.0
      ],
      "true_top_class": "genuine",
      "weight": 1.0
    },
    {
      "task_number": 228,
      "predicted_probs": [
        0.4577556848526001,
        0.3837814927101135,
        0.15846286714076996
      ],
      "predicted_class": "genuine",
      "true_soft_label": [
        0.0,
        0.0,
        1.0
      ],
      "true_top_class": "masking",
      "weight": 1.0
    },
    {
      "task_number": 239,
      "predicted_probs": [
        0.46105366945266724,
        0.37900862097740173,
        0.15993769466876984
      ],
      "predicted_class": "genuine",
      "true_soft_label": [
        1.0,
        0.0,
        0.0
      ],
      "true_top_class": "genuine",
      "weight": 1.0
    },
    {
      "task_number": 279,
      "predicted_probs": [
        0.4505062699317932,
        0.38374805450439453,
        0.16574569046497345
      ],
      "predicted_class": "genuine",
      "true_soft_label": [
        0.0,
        0.0,
        1.0
      ],
      "true_top_class": "masking",
      "weight": 1.0
    },
    {
      "task_number": 317,
      "predicted_probs": [
        0.4569243788719177,
        0.3761012852191925,
        0.16697432100772858
      ],
      "predicted_class": "genuine",
      "true_soft_label": [
        1.0,
        0.0,
        0.0
      ],
      "true_top_class": "genuine",
      "weight": 1.0
    },
    {
      "task_number": 329,
      "predicted_probs": [
        0.4582340717315674,
        0.3787636458873749,
        0.16300228238105774
      ],
      "predicted_class": "genuine",
      "true_soft_label": [
        0.0,
        1.0,
        0.0
      ],
      "true_top_class": "polite",
      "weight": 1.0
    },
    {
      "task_number": 350,
      "predicted_probs": [
        0.4684887230396271,
        0.3758437931537628,
        0.1556674987077713
      ],
      "predicted_class": "genuine",
      "true_soft_label": [
        0.0,
        0.0,
        1.0
      ],
      "true_top_class": "masking",
      "weight": 1.0
    },
    {
      "task_number": 363,
      "predicted_probs": [
        0.4507673382759094,
        0.38116902112960815,
        0.16806362569332123
      ],
      "predicted_class": "genuine",
      "true_soft_label": [
        1.0,
        0.0,
        0.0
      ],
      "true_top_class": "genuine",
      "weight": 1.0
    },
    {
      "task_number": 371,
      "predicted_probs": [
        0.4314865171909332,
        0.3858526051044464,
        0.18266083300113678
      ],
      "predicted_class": "genuine",
      "true_soft_label": [
        0.0,
        1.0,
        0.0
      ],
      "true_top_class": "polite",
      "weight": 1.0
    },
    {
      "task_number": 372,
      "predicted_probs": [
        0.4433579742908478,
        0.3788934051990509,
        0.17774862051010132
      ],
      "predicted_class": "genuine",
      "true_soft_label": [
        1.0,
        0.0,
        0.0
      ],
      "true_top_class": "genuine",
      "weight": 1.0
    },
    {
      "task_number": 379,
      "predicted_probs": [
        0.4606284499168396,
        0.37631580233573914,
        0.1630556732416153
      ],
      "predicted_class": "genuine",
      "true_soft_label": [
        0.0,
        0.0,
        1.0
      ],
      "true_top_class": "masking",
      "weight": 1.0
    },
    {
      "task_number": 17,
      "predicted_probs": [
        0.4597591459751129,
        0.3721810579299927,
        0.16805985569953918
      ],
      "predicted_class": "genuine",
      "true_soft_label": [
        0.6000000238418579,
        0.20000000298023224,
        0.20000000298023224
      ],
      "true_top_class": "genuine",
      "weight": 1.0
    },
    {
      "task_number": 20,
      "predicted_probs": [
        0.4645595848560333,
        0.3748922646045685,
        0.160548135638237
      ],
      "predicted_class": "genuine",
      "true_soft_label": [
        0.6000000238418579,
        0.0,
        0.4000000059604645
      ],
      "true_top_class": "genuine",
      "weight": 1.0
    },
    {
      "task_number": 24,
      "predicted_probs": [
        0.45263010263442993,
        0.37896060943603516,
        0.1684093177318573
      ],
      "predicted_class": "genuine",
      "true_soft_label": [
        0.4000000059604645,
        0.4000000059604645,
        0.20000000298023224
      ],
      "true_top_class": "genuine",
      "weight": 1.0
    },
    {
      "task_number": 52,
      "predicted_probs": [
        0.4570835828781128,
        0.3770507574081421,
        0.1658656895160675
      ],
      "predicted_class": "genuine",
      "true_soft_label": [
        0.0,
        1.0,
        0.0
      ],
      "true_top_class": "polite",
      "weight": 1.0
    },
    {
      "task_number": 54,
      "predicted_probs": [
        0.44940710067749023,
        0.3736163377761841,
        0.1769765019416809
      ],
      "predicted_class": "genuine",
      "true_soft_label": [
        0.3333333432674408,
        0.6666666865348816,
        0.0
      ],
      "true_top_class": "polite",
      "weight": 1.0
    },
    {
      "task_number": 58,
      "predicted_probs": [
        0.4551226794719696,
        0.37574928998947144,
        0.16912800073623657
      ],
      "predicted_class": "genuine",
      "true_soft_label": [
        0.3333333432674408,
        0.3333333432674408,
        0.3333333432674408
      ],
      "true_top_class": "genuine",
      "weight": 1.0
    },
    {
      "task_number": 62,
      "predicted_probs": [
        0.4426383376121521,
        0.38347285985946655,
        0.17388886213302612
      ],
      "predicted_class": "genuine",
      "true_soft_label": [
        0.3333333432674408,
        0.3333333432674408,
        0.3333333432674408
      ],
      "true_top_class": "genuine",
      "weight": 1.0
    },
    {
      "task_number": 67,
      "predicted_probs": [
        0.4508143961429596,
        0.381020724773407,
        0.16816486418247223
      ],
      "predicted_class": "genuine",
      "true_soft_label": [
        0.6666666865348816,
        0.0,
        0.3333333432674408
      ],
      "true_top_class": "genuine",
      "weight": 1.0
    },
    {
      "task_number": 76,
      "predicted_probs": [
        0.45106759667396545,
        0.3807465732097626,
        0.16818581521511078
      ],
      "predicted_class": "genuine",
      "true_soft_label": [
        0.5,
        0.5,
        0.0
      ],
      "true_top_class": "genuine",
      "weight": 1.0
    },
    {
      "task_number": 104,
      "predicted_probs": [
        0.4375661015510559,
        0.3817881941795349,
        0.1806456744670868
      ],
      "predicted_class": "genuine",
      "true_soft_label": [
        0.0,
        1.0,
        0.0
      ],
      "true_top_class": "polite",
      "weight": 1.0
    },
    {
      "task_number": 134,
      "predicted_probs": [
        0.43434834480285645,
        0.3819587230682373,
        0.18369294703006744
      ],
      "predicted_class": "genuine",
      "true_soft_label": [
        1.0,
        0.0,
        0.0
      ],
      "true_top_class": "genuine",
      "weight": 1.0
    },
    {
      "task_number": 179,
      "predicted_probs": [
        0.4382590055465698,
        0.37981608510017395,
        0.18192486464977264
      ],
      "predicted_class": "genuine",
      "true_soft_label": [
        0.0,
        0.0,
        1.0
      ],
      "true_top_class": "masking",
      "weight": 1.0
    },
    {
      "task_number": 233,
      "predicted_probs": [
        0.4523913562297821,
        0.37973737716674805,
        0.16787126660346985
      ],
      "predicted_class": "genuine",
      "true_soft_label": [
        0.0,
        1.0,
        0.0
      ],
      "true_top_class": "polite",
      "weight": 1.0
    },
    {
      "task_number": 236,
      "predicted_probs": [
        0.45669716596603394,
        0.377519816160202,
        0.16578301787376404
      ],
      "predicted_class": "genuine",
      "true_soft_label": [
        1.0,
        0.0,
        0.0
      ],
      "true_top_class": "genuine",
      "weight": 1.0
    },
    {
      "task_number": 244,
      "predicted_probs": [
        0.44533661007881165,
        0.38090160489082336,
        0.17376179993152618
      ],
      "predicted_class": "genuine",
      "true_soft_label": [
        1.0,
        0.0,
        0.0
      ],
      "true_top_class": "genuine",
      "weight": 1.0
    },
    {
      "task_number": 270,
      "predicted_probs": [
        0.4610655903816223,
        0.3760029375553131,
        0.162931427359581
      ],
      "predicted_class": "genuine",
      "true_soft_label": [
        1.0,
        0.0,
        0.0
      ],
      "true_top_class": "genuine",
      "weight": 1.0
    },
    {
      "task_number": 289,
      "predicted_probs": [
        0.43937259912490845,
        0.3814224302768707,
        0.17920495569705963
      ],
      "predicted_class": "genuine",
      "true_soft_label": [
        0.0,
        0.0,
        1.0
      ],
      "true_top_class": "masking",
      "weight": 1.0
    },
    {
      "task_number": 302,
      "predicted_probs": [
        0.4584401249885559,
        0.37583816051483154,
        0.16572177410125732
      ],
      "predicted_class": "genuine",
      "true_soft_label": [
        0.0,
        1.0,
        0.0
      ],
      "true_top_class": "polite",
      "weight": 1.0
    },
    {
      "task_number": 303,
      "predicted_probs": [
        0.45861122012138367,
        0.3773156404495239,
        0.16407319903373718
      ],
      "predicted_class": "genuine",
      "true_soft_label": [
        0.0,
        1.0,
        0.0
      ],
      "true_top_class": "polite",
      "weight": 1.0
    },
    {
      "task_number": 315,
      "predicted_probs": [
        0.44457074999809265,
        0.3777204751968384,
        0.17770877480506897
      ],
      "predicted_class": "genuine",
      "true_soft_label": [
        1.0,
        0.0,
        0.0
      ],
      "true_top_class": "genuine",
      "weight": 1.0
    },
    {
      "task_number": 318,
      "predicted_probs": [
        0.44900140166282654,
        0.37806907296180725,
        0.1729295253753662
      ],
      "predicted_class": "genuine",
      "true_soft_label": [
        1.0,
        0.0,
        0.0
      ],
      "true_top_class": "genuine",
      "weight": 1.0
    },
    {
      "task_number": 322,
      "predicted_probs": [
        0.4537101089954376,
        0.3803827166557312,
        0.16590715944766998
      ],
      "predicted_class": "genuine",
      "true_soft_label": [
        1.0,
        0.0,
        0.0
      ],
      "true_top_class": "genuine",
      "weight": 1.0
    },
    {
      "task_number": 360,
      "predicted_probs": [
        0.45034080743789673,
        0.37943771481513977,
        0.1702214628458023
      ],
      "predicted_class": "genuine",
      "true_soft_label": [
        0.0,
        0.0,
        1.0
      ],
      "true_top_class": "masking",
      "weight": 1.0
    },
    {
      "task_number": 361,
      "predicted_probs": [
        0.4447447955608368,
        0.38183480501174927,
        0.17342042922973633
      ],
      "predicted_class": "genuine",
      "true_soft_label": [
        0.0,
        1.0,
        0.0
      ],
      "true_top_class": "polite",
      "weight": 1.0
    },
    {
      "task_number": 366,
      "predicted_probs": [
        0.43766865134239197,
        0.3859765827655792,
        0.17635475099086761
      ],
      "predicted_class": "genuine",
      "true_soft_label": [
        0.0,
        1.0,
        0.0
      ],
      "true_top_class": "polite",
      "weight": 1.0
    },
    {
      "task_number": 375,
      "predicted_probs": [
        0.446316659450531,
        0.3777106702327728,
        0.17597270011901855
      ],
      "predicted_class": "genuine",
      "true_soft_label": [
        1.0,
        0.0,
        0.0
      ],
      "true_top_class": "genuine",
      "weight": 1.0
    },
    {
      "task_number": 2,
      "predicted_probs": [
        0.463331937789917,
        0.3702681362628937,
        0.16639989614486694
      ],
      "predicted_class": "genuine",
      "true_soft_label": [
        0.800000011920929,
        0.0,
        0.20000000298023224
      ],
      "true_top_class": "genuine",
      "weight": 1.0
    },
    {
      "task_number": 23,
      "predicted_probs": [
        0.4562249779701233,
        0.3711814880371094,
        0.17259342968463898
      ],
      "predicted_class": "genuine",
      "true_soft_label": [
        0.0,
        0.800000011920929,
        0.20000000298023224
      ],
      "true_top_class": "polite",
      "weight": 1.0
    },
    {
      "task_number": 41,
      "predicted_probs": [
        0.440181702375412,
        0.37364378571510315,
        0.18617454171180725
      ],
      "predicted_class": "genuine",
      "true_soft_label": [
        0.0,
        1.0,
        0.0
      ],
      "true_top_class": "polite",
      "weight": 1.0
    },
    {
      "task_number": 56,
      "predicted_probs": [
        0.46187078952789307,
        0.3621489405632019,
        0.1759803146123886
      ],
      "predicted_class": "genuine",
      "true_soft_label": [
        0.0,
        1.0,
        0.0
      ],
      "true_top_class": "polite",
      "weight": 1.0
    },
    {
      "task_number": 61,
      "predicted_probs": [
        0.4408186674118042,
        0.3768138289451599,
        0.1823674589395523
      ],
      "predicted_class": "genuine",
      "true_soft_label": [
        0.0,
        0.0,
        1.0
      ],
      "true_top_class": "masking",
      "weight": 1.0
    },
    {
      "task_number": 75,
      "predicted_probs": [
        0.45243358612060547,
        0.3771154582500458,
        0.17045100033283234
      ],
      "predicted_class": "genuine",
      "true_soft_label": [
        0.0,
        1.0,
        0.0
      ],
      "true_top_class": "polite",
      "weight": 1.0
    },
    {
      "task_number": 103,
      "predicted_probs": [
        0.44570472836494446,
        0.37049156427383423,
        0.18380366265773773
      ],
      "predicted_class": "genuine",
      "true_soft_label": [
        0.0,
        1.0,
        0.0
      ],
      "true_top_class": "polite",
      "weight": 1.0
    },
    {
      "task_number": 123,
      "predicted_probs": [
        0.45866623520851135,
        0.372287392616272,
        0.16904638707637787
      ],
      "predicted_class": "genuine",
      "true_soft_label": [
        1.0,
        0.0,
        0.0
      ],
      "true_top_class": "genuine",
      "weight": 1.0
    },
    {
      "task_number": 129,
      "predicted_probs": [
        0.4552344083786011,
        0.3686200678348541,
        0.1761454939842224
      ],
      "predicted_class": "genuine",
      "true_soft_label": [
        0.0,
        1.0,
        0.0
      ],
      "true_top_class": "polite",
      "weight": 1.0
    },
    {
      "task_number": 133,
      "predicted_probs": [
        0.4388401210308075,
        0.3724658489227295,
        0.18869401514530182
      ],
      "predicted_class": "genuine",
      "true_soft_label": [
        1.0,
        0.0,
        0.0
      ],
      "true_top_class": "genuine",
      "weight": 1.0
    },
    {
      "task_number": 159,
      "predicted_probs": [
        0.46558117866516113,
        0.3640407919883728,
        0.17037804424762726
      ],
      "predicted_class": "genuine",
      "true_soft_label": [
        0.0,
        1.0,
        0.0
      ],
      "true_top_class": "polite",
      "weight": 1.0
    },
    {
      "task_number": 174,
      "predicted_probs": [
        0.4093480706214905,
        0.37011003494262695,
        0.22054195404052734
      ],
      "predicted_class": "genuine",
      "true_soft_label": [
        0.0,
        1.0,
        0.0
      ],
      "true_top_class": "polite",
      "weight": 1.0
    },
    {
      "task_number": 175,
      "predicted_probs": [
        0.4113115072250366,
        0.37527579069137573,
        0.21341261267662048
      ],
      "predicted_class": "genuine",
      "true_soft_label": [
        1.0,
        0.0,
        0.0
      ],
      "true_top_class": "genuine",
      "weight": 1.0
    },
    {
      "task_number": 206,
      "predicted_probs": [
        0.4441170394420624,
        0.37035948038101196,
        0.18552346527576447
      ],
      "predicted_class": "genuine",
      "true_soft_label": [
        0.0,
        1.0,
        0.0
      ],
      "true_top_class": "polite",
      "weight": 1.0
    },
    {
      "task_number": 211,
      "predicted_probs": [
        0.46990495920181274,
        0.3624683618545532,
        0.16762669384479523
      ],
      "predicted_class": "genuine",
      "true_soft_label": [
        0.0,
        0.0,
        1.0
      ],
      "true_top_class": "masking",
      "weight": 1.0
    },
    {
      "task_number": 219,
      "predicted_probs": [
        0.4605661928653717,
        0.369920015335083,
        0.1695137619972229
      ],
      "predicted_class": "genuine",
      "true_soft_label": [
        1.0,
        0.0,
        0.0
      ],
      "true_top_class": "genuine",
      "weight": 1.0
    },
    {
      "task_number": 222,
      "predicted_probs": [
        0.4560064971446991,
        0.3694095015525818,
        0.17458400130271912
      ],
      "predicted_class": "genuine",
      "true_soft_label": [
        0.0,
        1.0,
        0.0
      ],
      "true_top_class": "polite",
      "weight": 1.0
    },
    {
      "task_number": 268,
      "predicted_probs": [
        0.45208075642585754,
        0.36907780170440674,
        0.17884142696857452
      ],
      "predicted_class": "genuine",
      "true_soft_label": [
        1.0,
        0.0,
        0.0
      ],
      "true_top_class": "genuine",
      "weight": 1.0
    },
    {
      "task_number": 269,
      "predicted_probs": [
        0.4642972946166992,
        0.36716678738594055,
        0.16853591799736023
      ],
      "predicted_class": "genuine",
      "true_soft_label": [
        0.0,
        0.0,
        1.0
      ],
      "true_top_class": "masking",
      "weight": 1.0
    },
    {
      "task_number": 272,
      "predicted_probs": [
        0.4593408703804016,
        0.3689627945423126,
        0.17169632017612457
      ],
      "predicted_class": "genuine",
      "true_soft_label": [
        1.0,
        0.0,
        0.0
      ],
      "true_top_class": "genuine",
      "weight": 1.0
    },
    {
      "task_number": 285,
      "predicted_probs": [
        0.4344325661659241,
        0.375383585691452,
        0.1901838332414627
      ],
      "predicted_class": "genuine",
      "true_soft_label": [
        0.0,
        0.0,
        1.0
      ],
      "true_top_class": "masking",
      "weight": 1.0
    },
    {
      "task_number": 298,
      "predicted_probs": [
        0.4717804193496704,
        0.3641916811466217,
        0.1640278398990631
      ],
      "predicted_class": "genuine",
      "true_soft_label": [
        0.0,
        1.0,
        0.0
      ],
      "true_top_class": "polite",
      "weight": 1.0
    },
    {
      "task_number": 337,
      "predicted_probs": [
        0.46475157141685486,
        0.36693522334098816,
        0.1683131605386734
      ],
      "predicted_class": "genuine",
      "true_soft_label": [
        1.0,
        0.0,
        0.0
      ],
      "true_top_class": "genuine",
      "weight": 1.0
    },
    {
      "task_number": 378,
      "predicted_probs": [
        0.45274296402931213,
        0.3742499053478241,
        0.17300720512866974
      ],
      "predicted_class": "genuine",
      "true_soft_label": [
        1.0,
        0.0,
        0.0
      ],
      "true_top_class": "genuine",
      "weight": 1.0
    },
    {
      "task_number": 392,
      "predicted_probs": [
        0.462745726108551,
        0.3655730187892914,
        0.17168128490447998
      ],
      "predicted_class": "genuine",
      "true_soft_label": [
        1.0,
        0.0,
        0.0
      ],
      "true_top_class": "genuine",
      "weight": 1.0
    },
    {
      "task_number": 398,
      "predicted_probs": [
        0.44708892703056335,
        0.37239015102386475,
        0.1805209517478943
      ],
      "predicted_class": "genuine",
      "true_soft_label": [
        0.0,
        1.0,
        0.0
      ],
      "true_top_class": "polite",
      "weight": 1.0
    }
  ]
}