{
  "video_id": "11499.1",
  "fps": 30.0,
  "total_frames": 53588,
  "total_duration_sec": 1786.267,
  "smoothing_sigma_sec": 0.133,
  "threshold": 1.0,
  "min_duration_sec": 0.5,
  "num_segments": 2,
  "total_smile_sec": 2.001,
  "segments": [
    {
      "start_ts": 659.2,
      "end_ts": 660.267,
      "peak_r": 1.38,
      "mean_r": 1.205,
      "mass_r": 1.2853
    },
    {
      "start_ts": 1599.833,
      "end_ts": 1600.767,
      "peak_r": 1.33,
      "mean_r": 1.1761,
      "mass_r": 1.0977
    }
  ]
}