{
  "video_id": "2460.1",
  "fps": 30.0,
  "total_frames": 54616,
  "total_duration_sec": 1820.533,
  "smoothing_sigma_sec": 0.133,
  "threshold": 1.0,
  "min_duration_sec": 0.5,
  "num_segments": 128,
  "total_smile_sec": 178.496,
  "segments": [
    {
      "start_ts": 72.9,
      "end_ts": 74.367,
      "peak_r": 1.71,
      "mean_r": 1.2609,
      "mass_r": 1.8493
    },
    {
      "start_ts": 101.433,
      "end_ts": 102.2,
      "peak_r": 1.14,
      "mean_r": 1.0917,
      "mass_r": 0.837
    },
    {
      "start_ts": 102.6,
      "end_ts": 104.3,
      "peak_r": 1.32,
      "mean_r": 1.2041,
      "mass_r": 2.047
    },
    {
      "start_ts": 125.4,
      "end_ts": 126.033,
      "peak_r": 1.11,
      "mean_r": 1.0305,
      "mass_r": 0.6527
    },
    {
      "start_ts": 170.533,
      "end_ts": 172.7,
      "peak_r": 1.37,
      "mean_r": 1.2002,
      "mass_r": 2.6003
    },
    {
      "start_ts": 174.9,
      "end_ts": 176.667,
      "peak_r": 1.2,
      "mean_r": 1.0849,
      "mass_r": 1.9167
    },
    {
      "start_ts": 188.967,
      "end_ts": 189.9,
      "peak_r": 1.2,
      "mean_r": 1.0925,
      "mass_r": 1.0197
    },
    {
      "start_ts": 211.067,
      "end_ts": 212.833,
      "peak_r": 1.31,
      "mean_r": 1.1449,
      "mass_r": 2.0227
    },
    {
      "start_ts": 215.3,
      "end_ts": 216.467,
      "peak_r": 1.18,
      "mean_r": 1.0566,
      "mass_r": 1.2327
    },
    {
      "start_ts": 217.4,
      "end_ts": 218.233,
      "peak_r": 1.12,
      "mean_r": 1.0408,
      "mass_r": 0.8673
    },
    {
      "start_ts": 239.833,
      "end_ts": 241.4,
      "peak_r": 1.24,
      "mean_r": 1.1379,
      "mass_r": 1.7827
    },
    {
      "start_ts": 272.333,
      "end_ts": 278.933,
      "peak_r": 1.55,
      "mean_r": 1.2354,
      "mass_r": 8.1533
    },
    {
      "start_ts": 280.7,
      "end_ts": 282.333,
      "peak_r": 1.45,
      "mean_r": 1.2104,
      "mass_r": 1.977
    },
    {
      "start_ts": 282.667,
      "end_ts": 283.233,
      "peak_r": 1.17,
      "mean_r": 1.0729,
      "mass_r": 0.608
    },
    {
      "start_ts": 285.267,
      "end_ts": 285.8,
      "peak_r": 1.28,
      "mean_r": 1.0625,
      "mass_r": 0.5667
    },
    {
      "start_ts": 288.733,
      "end_ts": 290.567,
      "peak_r": 1.3,
      "mean_r": 1.1422,
      "mass_r": 2.094
    },
    {
      "start_ts": 291.133,
      "end_ts": 291.8,
      "peak_r": 1.24,
      "mean_r": 1.0955,
      "mass_r": 0.7303
    },
    {
      "start_ts": 300.2,
      "end_ts": 301.0,
      "peak_r": 1.2,
      "mean_r": 1.1267,
      "mass_r": 0.9013
    },
    {
      "start_ts": 314.433,
      "end_ts": 315.967,
      "peak_r": 2.16,
      "mean_r": 1.3961,
      "mass_r": 2.1407
    },
    {
      "start_ts": 317.433,
      "end_ts": 318.633,
      "peak_r": 1.31,
      "mean_r": 1.1411,
      "mass_r": 1.3693
    },
    {
      "start_ts": 325.833,
      "end_ts": 326.667,
      "peak_r": 1.12,
      "mean_r": 1.0728,
      "mass_r": 0.894
    },
    {
      "start_ts": 346.033,
      "end_ts": 346.6,
      "peak_r": 1.21,
      "mean_r": 1.1047,
      "mass_r": 0.626
    },
    {
      "start_ts": 347.333,
      "end_ts": 348.167,
      "peak_r": 1.44,
      "mean_r": 1.148,
      "mass_r": 0.9567
    },
    {
      "start_ts": 362.5,
      "end_ts": 363.3,
      "peak_r": 1.51,
      "mean_r": 1.25,
      "mass_r": 1.0
    },
    {
      "start_ts": 370.1,
      "end_ts": 371.1,
      "peak_r": 1.65,
      "mean_r": 1.4327,
      "mass_r": 1.4327
    },
    {
      "start_ts": 421.267,
      "end_ts": 422.7,
      "peak_r": 1.22,
      "mean_r": 1.0705,
      "mass_r": 1.5343
    },
    {
      "start_ts": 442.967,
      "end_ts": 444.233,
      "peak_r": 1.15,
      "mean_r": 1.0466,
      "mass_r": 1.3257
    },
    {
      "start_ts": 444.833,
      "end_ts": 445.333,
      "peak_r": 1.12,
      "mean_r": 1.0653,
      "mass_r": 0.5327
    },
    {
      "start_ts": 451.567,
      "end_ts": 453.333,
      "peak_r": 1.28,
      "mean_r": 1.1328,
      "mass_r": 2.0013
    },
    {
      "start_ts": 454.467,
      "end_ts": 455.067,
      "peak_r": 1.35,
      "mean_r": 1.1161,
      "mass_r": 0.6697
    },
    {
      "start_ts": 471.467,
      "end_ts": 474.5,
      "peak_r": 1.37,
      "mean_r": 1.1287,
      "mass_r": 3.4237
    },
    {
      "start_ts": 475.9,
      "end_ts": 477.4,
      "peak_r": 1.24,
      "mean_r": 1.0924,
      "mass_r": 1.6387
    },
    {
      "start_ts": 478.9,
      "end_ts": 480.067,
      "peak_r": 1.12,
      "mean_r": 1.0591,
      "mass_r": 1.2357
    },
    {
      "start_ts": 480.233,
      "end_ts": 480.967,
      "peak_r": 1.16,
      "mean_r": 1.0382,
      "mass_r": 0.7613
    },
    {
      "start_ts": 516.267,
      "end_ts": 520.533,
      "peak_r": 2.32,
      "mean_r": 1.4643,
      "mass_r": 6.2477
    },
    {
      "start_ts": 520.7,
      "end_ts": 523.267,
      "peak_r": 1.68,
      "mean_r": 1.2832,
      "mass_r": 3.2937
    },
    {
      "start_ts": 523.333,
      "end_ts": 524.133,
      "peak_r": 1.45,
      "mean_r": 1.195,
      "mass_r": 0.956
    },
    {
      "start_ts": 525.967,
      "end_ts": 527.1,
      "peak_r": 1.13,
      "mean_r": 1.0482,
      "mass_r": 1.188
    },
    {
      "start_ts": 602.933,
      "end_ts": 603.667,
      "peak_r": 1.36,
      "mean_r": 1.1123,
      "mass_r": 0.8157
    },
    {
      "start_ts": 621.0,
      "end_ts": 621.533,
      "peak_r": 1.26,
      "mean_r": 1.135,
      "mass_r": 0.6053
    },
    {
      "start_ts": 621.667,
      "end_ts": 622.467,
      "peak_r": 1.26,
      "mean_r": 1.085,
      "mass_r": 0.868
    },
    {
      "start_ts": 623.067,
      "end_ts": 623.867,
      "peak_r": 1.35,
      "mean_r": 1.2371,
      "mass_r": 0.9897
    },
    {
      "start_ts": 631.8,
      "end_ts": 632.5,
      "peak_r": 1.13,
      "mean_r": 1.0333,
      "mass_r": 0.7233
    },
    {
      "start_ts": 701.467,
      "end_ts": 702.2,
      "peak_r": 1.58,
      "mean_r": 1.1895,
      "mass_r": 0.8723
    },
    {
      "start_ts": 718.1,
      "end_ts": 718.633,
      "peak_r": 1.28,
      "mean_r": 1.105,
      "mass_r": 0.5893
    },
    {
      "start_ts": 750.6,
      "end_ts": 751.433,
      "peak_r": 1.22,
      "mean_r": 1.0824,
      "mass_r": 0.902
    },
    {
      "start_ts": 794.4,
      "end_ts": 795.433,
      "peak_r": 1.21,
      "mean_r": 1.04,
      "mass_r": 1.0747
    },
    {
      "start_ts": 796.067,
      "end_ts": 796.8,
      "peak_r": 1.16,
      "mean_r": 1.0359,
      "mass_r": 0.7597
    },
    {
      "start_ts": 804.6,
      "end_ts": 805.4,
      "peak_r": 1.21,
      "mean_r": 1.1071,
      "mass_r": 0.8857
    },
    {
      "start_ts": 806.033,
      "end_ts": 807.733,
      "peak_r": 1.31,
      "mean_r": 1.1771,
      "mass_r": 2.001
    },
    {
      "start_ts": 808.367,
      "end_ts": 809.8,
      "peak_r": 1.25,
      "mean_r": 1.1149,
      "mass_r": 1.598
    },
    {
      "start_ts": 809.967,
      "end_ts": 811.9,
      "peak_r": 1.55,
      "mean_r": 1.1531,
      "mass_r": 2.2293
    },
    {
      "start_ts": 825.033,
      "end_ts": 825.6,
      "peak_r": 1.26,
      "mean_r": 1.0935,
      "mass_r": 0.6197
    },
    {
      "start_ts": 827.033,
      "end_ts": 830.933,
      "peak_r": 2.21,
      "mean_r": 1.3397,
      "mass_r": 5.225
    },
    {
      "start_ts": 831.033,
      "end_ts": 831.667,
      "peak_r": 1.28,
      "mean_r": 1.0574,
      "mass_r": 0.6697
    },
    {
      "start_ts": 837.3,
      "end_ts": 838.333,
      "peak_r": 1.28,
      "mean_r": 1.1513,
      "mass_r": 1.1897
    },
    {
      "start_ts": 838.467,
      "end_ts": 838.967,
      "peak_r": 1.22,
      "mean_r": 1.1187,
      "mass_r": 0.5593
    },
    {
      "start_ts": 840.5,
      "end_ts": 841.0,
      "peak_r": 1.15,
      "mean_r": 1.0687,
      "mass_r": 0.5343
    },
    {
      "start_ts": 848.2,
      "end_ts": 848.867,
      "peak_r": 1.15,
      "mean_r": 1.058,
      "mass_r": 0.7053
    },
    {
      "start_ts": 856.1,
      "end_ts": 856.633,
      "peak_r": 1.17,
      "mean_r": 1.05,
      "mass_r": 0.56
    },
    {
      "start_ts": 861.967,
      "end_ts": 862.633,
      "peak_r": 1.22,
      "mean_r": 1.1015,
      "mass_r": 0.7343
    },
    {
      "start_ts": 874.733,
      "end_ts": 875.6,
      "peak_r": 1.27,
      "mean_r": 1.0708,
      "mass_r": 0.928
    },
    {
      "start_ts": 877.467,
      "end_ts": 878.867,
      "peak_r": 1.45,
      "mean_r": 1.2617,
      "mass_r": 1.7663
    },
    {
      "start_ts": 879.8,
      "end_ts": 884.467,
      "peak_r": 2.02,
      "mean_r": 1.4604,
      "mass_r": 6.815
    },
    {
      "start_ts": 893.433,
      "end_ts": 894.567,
      "peak_r": 1.3,
      "mean_r": 1.1238,
      "mass_r": 1.2737
    },
    {
      "start_ts": 895.5,
      "end_ts": 897.2,
      "peak_r": 1.6,
      "mean_r": 1.3943,
      "mass_r": 2.3703
    },
    {
      "start_ts": 899.133,
      "end_ts": 902.367,
      "peak_r": 1.35,
      "mean_r": 1.1698,
      "mass_r": 3.7823
    },
    {
      "start_ts": 902.933,
      "end_ts": 905.0,
      "peak_r": 1.48,
      "mean_r": 1.2953,
      "mass_r": 2.677
    },
    {
      "start_ts": 905.467,
      "end_ts": 906.133,
      "peak_r": 1.27,
      "mean_r": 1.1,
      "mass_r": 0.7333
    },
    {
      "start_ts": 913.867,
      "end_ts": 914.533,
      "peak_r": 1.28,
      "mean_r": 1.128,
      "mass_r": 0.752
    },
    {
      "start_ts": 916.233,
      "end_ts": 916.733,
      "peak_r": 1.17,
      "mean_r": 1.1027,
      "mass_r": 0.5513
    },
    {
      "start_ts": 917.933,
      "end_ts": 920.7,
      "peak_r": 1.31,
      "mean_r": 1.1633,
      "mass_r": 3.2183
    },
    {
      "start_ts": 945.0,
      "end_ts": 947.867,
      "peak_r": 1.39,
      "mean_r": 1.1586,
      "mass_r": 3.3213
    },
    {
      "start_ts": 981.2,
      "end_ts": 982.233,
      "peak_r": 1.64,
      "mean_r": 1.4565,
      "mass_r": 1.505
    },
    {
      "start_ts": 989.567,
      "end_ts": 990.2,
      "peak_r": 1.25,
      "mean_r": 1.0842,
      "mass_r": 0.6867
    },
    {
      "start_ts": 993.967,
      "end_ts": 994.8,
      "peak_r": 1.14,
      "mean_r": 1.0928,
      "mass_r": 0.9107
    },
    {
      "start_ts": 1003.467,
      "end_ts": 1005.867,
      "peak_r": 1.33,
      "mean_r": 1.1107,
      "mass_r": 2.6657
    },
    {
      "start_ts": 1112.267,
      "end_ts": 1112.767,
      "peak_r": 1.49,
      "mean_r": 1.1993,
      "mass_r": 0.5997
    },
    {
      "start_ts": 1154.633,
      "end_ts": 1155.6,
      "peak_r": 1.45,
      "mean_r": 1.241,
      "mass_r": 1.1997
    },
    {
      "start_ts": 1160.8,
      "end_ts": 1161.333,
      "peak_r": 1.22,
      "mean_r": 1.1362,
      "mass_r": 0.606
    },
    {
      "start_ts": 1173.867,
      "end_ts": 1175.033,
      "peak_r": 1.27,
      "mean_r": 1.0929,
      "mass_r": 1.275
    },
    {
      "start_ts": 1178.133,
      "end_ts": 1179.5,
      "peak_r": 1.35,
      "mean_r": 1.2134,
      "mass_r": 1.6583
    },
    {
      "start_ts": 1195.333,
      "end_ts": 1196.1,
      "peak_r": 1.16,
      "mean_r": 1.0626,
      "mass_r": 0.8147
    },
    {
      "start_ts": 1198.3,
      "end_ts": 1199.433,
      "peak_r": 1.27,
      "mean_r": 1.16,
      "mass_r": 1.3147
    },
    {
      "start_ts": 1223.367,
      "end_ts": 1224.233,
      "peak_r": 1.16,
      "mean_r": 1.0635,
      "mass_r": 0.9217
    },
    {
      "start_ts": 1243.967,
      "end_ts": 1245.6,
      "peak_r": 1.35,
      "mean_r": 1.1641,
      "mass_r": 1.9013
    },
    {
      "start_ts": 1246.167,
      "end_ts": 1248.233,
      "peak_r": 1.29,
      "mean_r": 1.1531,
      "mass_r": 2.383
    },
    {
      "start_ts": 1250.4,
      "end_ts": 1252.833,
      "peak_r": 1.39,
      "mean_r": 1.136,
      "mass_r": 2.7643
    },
    {
      "start_ts": 1254.433,
      "end_ts": 1255.533,
      "peak_r": 1.37,
      "mean_r": 1.1333,
      "mass_r": 1.2467
    },
    {
      "start_ts": 1256.733,
      "end_ts": 1257.333,
      "peak_r": 1.1,
      "mean_r": 1.0544,
      "mass_r": 0.6327
    },
    {
      "start_ts": 1272.133,
      "end_ts": 1273.567,
      "peak_r": 1.32,
      "mean_r": 1.1851,
      "mass_r": 1.6987
    },
    {
      "start_ts": 1274.533,
      "end_ts": 1294.1,
      "peak_r": 2.21,
      "mean_r": 1.575,
      "mass_r": 30.817
    },
    {
      "start_ts": 1387.1,
      "end_ts": 1387.8,
      "peak_r": 1.3,
      "mean_r": 1.1605,
      "mass_r": 0.8123
    },
    {
      "start_ts": 1395.1,
      "end_ts": 1395.8,
      "peak_r": 1.12,
      "mean_r": 1.0324,
      "mass_r": 0.7227
    },
    {
      "start_ts": 1404.367,
      "end_ts": 1405.133,
      "peak_r": 1.23,
      "mean_r": 1.1035,
      "mass_r": 0.846
    },
    {
      "start_ts": 1421.4,
      "end_ts": 1422.733,
      "peak_r": 2.56,
      "mean_r": 1.8453,
      "mass_r": 2.4603
    },
    {
      "start_ts": 1429.267,
      "end_ts": 1430.067,
      "peak_r": 1.91,
      "mean_r": 1.4458,
      "mass_r": 1.1567
    },
    {
      "start_ts": 1430.167,
      "end_ts": 1433.233,
      "peak_r": 1.71,
      "mean_r": 1.2424,
      "mass_r": 3.81
    },
    {
      "start_ts": 1464.067,
      "end_ts": 1465.367,
      "peak_r": 1.39,
      "mean_r": 1.1756,
      "mass_r": 1.5283
    },
    {
      "start_ts": 1498.733,
      "end_ts": 1499.667,
      "peak_r": 1.66,
      "mean_r": 1.2618,
      "mass_r": 1.1777
    },
    {
      "start_ts": 1566.9,
      "end_ts": 1567.7,
      "peak_r": 1.3,
      "mean_r": 1.1796,
      "mass_r": 0.9437
    },
    {
      "start_ts": 1586.033,
      "end_ts": 1586.8,
      "peak_r": 1.36,
      "mean_r": 1.2404,
      "mass_r": 0.951
    },
    {
      "start_ts": 1604.267,
      "end_ts": 1605.9,
      "peak_r": 1.36,
      "mean_r": 1.1953,
      "mass_r": 1.9523
    },
    {
      "start_ts": 1615.6,
      "end_ts": 1617.333,
      "peak_r": 1.36,
      "mean_r": 1.116,
      "mass_r": 1.9343
    },
    {
      "start_ts": 1617.533,
      "end_ts": 1619.533,
      "peak_r": 1.47,
      "mean_r": 1.243,
      "mass_r": 2.486
    },
    {
      "start_ts": 1619.967,
      "end_ts": 1621.567,
      "peak_r": 1.72,
      "mean_r": 1.4383,
      "mass_r": 2.3013
    },
    {
      "start_ts": 1623.633,
      "end_ts": 1624.2,
      "peak_r": 1.54,
      "mean_r": 1.3365,
      "mass_r": 0.7573
    },
    {
      "start_ts": 1625.433,
      "end_ts": 1626.2,
      "peak_r": 1.36,
      "mean_r": 1.177,
      "mass_r": 0.9023
    },
    {
      "start_ts": 1634.267,
      "end_ts": 1634.767,
      "peak_r": 1.49,
      "mean_r": 1.194,
      "mass_r": 0.597
    },
    {
      "start_ts": 1671.5,
      "end_ts": 1672.1,
      "peak_r": 1.08,
      "mean_r": 1.0439,
      "mass_r": 0.6263
    },
    {
      "start_ts": 1674.467,
      "end_ts": 1675.9,
      "peak_r": 1.5,
      "mean_r": 1.1551,
      "mass_r": 1.6557
    },
    {
      "start_ts": 1693.067,
      "end_ts": 1693.567,
      "peak_r": 1.14,
      "mean_r": 1.0513,
      "mass_r": 0.5257
    },
    {
      "start_ts": 1702.167,
      "end_ts": 1702.767,
      "peak_r": 1.28,
      "mean_r": 1.14,
      "mass_r": 0.684
    },
    {
      "start_ts": 1710.567,
      "end_ts": 1711.333,
      "peak_r": 1.22,
      "mean_r": 1.1622,
      "mass_r": 0.891
    },
    {
      "start_ts": 1722.667,
      "end_ts": 1723.433,
      "peak_r": 1.2,
      "mean_r": 1.0578,
      "mass_r": 0.811
    },
    {
      "start_ts": 1724.167,
      "end_ts": 1725.467,
      "peak_r": 1.38,
      "mean_r": 1.1441,
      "mass_r": 1.4873
    },
    {
      "start_ts": 1728.0,
      "end_ts": 1728.633,
      "peak_r": 1.25,
      "mean_r": 1.1089,
      "mass_r": 0.7023
    },
    {
      "start_ts": 1731.3,
      "end_ts": 1731.967,
      "peak_r": 1.3,
      "mean_r": 1.1055,
      "mass_r": 0.737
    },
    {
      "start_ts": 1747.067,
      "end_ts": 1747.9,
      "peak_r": 1.2,
      "mean_r": 1.0568,
      "mass_r": 0.8807
    },
    {
      "start_ts": 1748.067,
      "end_ts": 1748.933,
      "peak_r": 1.23,
      "mean_r": 1.12,
      "mass_r": 0.9707
    },
    {
      "start_ts": 1751.667,
      "end_ts": 1752.267,
      "peak_r": 1.34,
      "mean_r": 1.1367,
      "mass_r": 0.682
    },
    {
      "start_ts": 1753.533,
      "end_ts": 1755.367,
      "peak_r": 1.36,
      "mean_r": 1.1996,
      "mass_r": 2.1993
    },
    {
      "start_ts": 1755.533,
      "end_ts": 1757.3,
      "peak_r": 1.44,
      "mean_r": 1.2109,
      "mass_r": 2.1393
    },
    {
      "start_ts": 1760.767,
      "end_ts": 1761.367,
      "peak_r": 1.36,
      "mean_r": 1.2589,
      "mass_r": 0.7553
    },
    {
      "start_ts": 1765.467,
      "end_ts": 1766.367,
      "peak_r": 1.23,
      "mean_r": 1.1185,
      "mass_r": 1.0067
    },
    {
      "start_ts": 1792.033,
      "end_ts": 1792.6,
      "peak_r": 1.16,
      "mean_r": 1.1129,
      "mass_r": 0.6307
    },
    {
      "start_ts": 1793.0,
      "end_ts": 1794.6,
      "peak_r": 1.21,
      "mean_r": 1.0833,
      "mass_r": 1.7333
    },
    {
      "start_ts": 1798.767,
      "end_ts": 1799.667,
      "peak_r": 1.26,
      "mean_r": 1.1167,
      "mass_r": 1.005
    }
  ]
}