{
  "video_id": "2980.1",
  "fps": 30.0,
  "total_frames": 51777,
  "total_duration_sec": 1725.9,
  "smoothing_sigma_sec": 0.133,
  "threshold": 1.0,
  "min_duration_sec": 0.5,
  "num_segments": 364,
  "total_smile_sec": 1039.972,
  "segments": [
    {
      "start_ts": 108.767,
      "end_ts": 112.7,
      "peak_r": 1.67,
      "mean_r": 1.2398,
      "mass_r": 4.8767
    },
    {
      "start_ts": 113.7,
      "end_ts": 117.667,
      "peak_r": 1.46,
      "mean_r": 1.1524,
      "mass_r": 4.571
    },
    {
      "start_ts": 118.7,
      "end_ts": 120.467,
      "peak_r": 1.3,
      "mean_r": 1.1387,
      "mass_r": 2.0117
    },
    {
      "start_ts": 121.5,
      "end_ts": 122.9,
      "peak_r": 1.49,
      "mean_r": 1.2107,
      "mass_r": 1.695
    },
    {
      "start_ts": 123.767,
      "end_ts": 134.367,
      "peak_r": 1.97,
      "mean_r": 1.3831,
      "mass_r": 14.6607
    },
    {
      "start_ts": 135.367,
      "end_ts": 140.833,
      "peak_r": 1.43,
      "mean_r": 1.2279,
      "mass_r": 6.7127
    },
    {
      "start_ts": 140.9,
      "end_ts": 154.033,
      "peak_r": 1.79,
      "mean_r": 1.3527,
      "mass_r": 17.7657
    },
    {
      "start_ts": 154.467,
      "end_ts": 159.067,
      "peak_r": 1.65,
      "mean_r": 1.2707,
      "mass_r": 5.8453
    },
    {
      "start_ts": 159.5,
      "end_ts": 163.9,
      "peak_r": 1.38,
      "mean_r": 1.1371,
      "mass_r": 5.0033
    },
    {
      "start_ts": 164.133,
      "end_ts": 164.633,
      "peak_r": 1.2,
      "mean_r": 1.0973,
      "mass_r": 0.5487
    },
    {
      "start_ts": 166.667,
      "end_ts": 167.3,
      "peak_r": 1.1,
      "mean_r": 1.0389,
      "mass_r": 0.658
    },
    {
      "start_ts": 169.0,
      "end_ts": 173.867,
      "peak_r": 1.49,
      "mean_r": 1.1814,
      "mass_r": 5.7493
    },
    {
      "start_ts": 175.433,
      "end_ts": 177.567,
      "peak_r": 1.24,
      "mean_r": 1.0619,
      "mass_r": 2.2653
    },
    {
      "start_ts": 180.9,
      "end_ts": 181.533,
      "peak_r": 1.2,
      "mean_r": 1.0637,
      "mass_r": 0.6737
    },
    {
      "start_ts": 182.633,
      "end_ts": 183.533,
      "peak_r": 1.34,
      "mean_r": 1.1452,
      "mass_r": 1.0307
    },
    {
      "start_ts": 184.467,
      "end_ts": 188.0,
      "peak_r": 1.46,
      "mean_r": 1.3152,
      "mass_r": 4.647
    },
    {
      "start_ts": 188.8,
      "end_ts": 189.8,
      "peak_r": 1.27,
      "mean_r": 1.132,
      "mass_r": 1.132
    },
    {
      "start_ts": 190.933,
      "end_ts": 191.433,
      "peak_r": 1.2,
      "mean_r": 1.0967,
      "mass_r": 0.5483
    },
    {
      "start_ts": 192.767,
      "end_ts": 202.7,
      "peak_r": 2.01,
      "mean_r": 1.466,
      "mass_r": 14.5627
    },
    {
      "start_ts": 204.733,
      "end_ts": 205.233,
      "peak_r": 1.29,
      "mean_r": 1.1987,
      "mass_r": 0.5993
    },
    {
      "start_ts": 205.867,
      "end_ts": 208.167,
      "peak_r": 1.63,
      "mean_r": 1.2907,
      "mass_r": 2.9687
    },
    {
      "start_ts": 208.4,
      "end_ts": 209.6,
      "peak_r": 1.33,
      "mean_r": 1.1578,
      "mass_r": 1.3893
    },
    {
      "start_ts": 210.5,
      "end_ts": 212.267,
      "peak_r": 1.67,
      "mean_r": 1.2181,
      "mass_r": 2.152
    },
    {
      "start_ts": 212.4,
      "end_ts": 213.233,
      "peak_r": 1.24,
      "mean_r": 1.0916,
      "mass_r": 0.9097
    },
    {
      "start_ts": 213.7,
      "end_ts": 214.5,
      "peak_r": 1.29,
      "mean_r": 1.1642,
      "mass_r": 0.9313
    },
    {
      "start_ts": 214.967,
      "end_ts": 215.967,
      "peak_r": 1.47,
      "mean_r": 1.2337,
      "mass_r": 1.2337
    },
    {
      "start_ts": 218.033,
      "end_ts": 218.767,
      "peak_r": 1.27,
      "mean_r": 1.1023,
      "mass_r": 0.8083
    },
    {
      "start_ts": 220.667,
      "end_ts": 222.633,
      "peak_r": 1.34,
      "mean_r": 1.2027,
      "mass_r": 2.3653
    },
    {
      "start_ts": 224.633,
      "end_ts": 225.4,
      "peak_r": 1.16,
      "mean_r": 1.1074,
      "mass_r": 0.849
    },
    {
      "start_ts": 226.133,
      "end_ts": 229.467,
      "peak_r": 1.38,
      "mean_r": 1.1938,
      "mass_r": 3.9793
    },
    {
      "start_ts": 231.4,
      "end_ts": 231.967,
      "peak_r": 1.33,
      "mean_r": 1.2041,
      "mass_r": 0.6823
    },
    {
      "start_ts": 232.4,
      "end_ts": 234.433,
      "peak_r": 1.47,
      "mean_r": 1.1823,
      "mass_r": 2.404
    },
    {
      "start_ts": 235.2,
      "end_ts": 235.767,
      "peak_r": 1.29,
      "mean_r": 1.1859,
      "mass_r": 0.672
    },
    {
      "start_ts": 236.4,
      "end_ts": 242.567,
      "peak_r": 1.76,
      "mean_r": 1.3475,
      "mass_r": 8.3093
    },
    {
      "start_ts": 246.4,
      "end_ts": 247.033,
      "peak_r": 1.27,
      "mean_r": 1.1263,
      "mass_r": 0.7133
    },
    {
      "start_ts": 251.433,
      "end_ts": 252.367,
      "peak_r": 1.27,
      "mean_r": 1.0789,
      "mass_r": 1.007
    },
    {
      "start_ts": 252.8,
      "end_ts": 254.967,
      "peak_r": 1.3,
      "mean_r": 1.1529,
      "mass_r": 2.498
    },
    {
      "start_ts": 260.633,
      "end_ts": 261.967,
      "peak_r": 1.31,
      "mean_r": 1.1353,
      "mass_r": 1.5137
    },
    {
      "start_ts": 262.867,
      "end_ts": 263.9,
      "peak_r": 1.25,
      "mean_r": 1.1532,
      "mass_r": 1.1917
    },
    {
      "start_ts": 267.7,
      "end_ts": 268.833,
      "peak_r": 1.39,
      "mean_r": 1.2285,
      "mass_r": 1.3923
    },
    {
      "start_ts": 269.5,
      "end_ts": 271.067,
      "peak_r": 1.25,
      "mean_r": 1.1213,
      "mass_r": 1.7567
    },
    {
      "start_ts": 272.1,
      "end_ts": 272.967,
      "peak_r": 1.15,
      "mean_r": 1.0685,
      "mass_r": 0.926
    },
    {
      "start_ts": 279.4,
      "end_ts": 280.1,
      "peak_r": 1.24,
      "mean_r": 1.1181,
      "mass_r": 0.7827
    },
    {
      "start_ts": 283.1,
      "end_ts": 284.1,
      "peak_r": 1.39,
      "mean_r": 1.19,
      "mass_r": 1.19
    },
    {
      "start_ts": 286.967,
      "end_ts": 288.367,
      "peak_r": 1.25,
      "mean_r": 1.1421,
      "mass_r": 1.599
    },
    {
      "start_ts": 289.167,
      "end_ts": 291.833,
      "peak_r": 1.31,
      "mean_r": 1.1364,
      "mass_r": 3.0303
    },
    {
      "start_ts": 292.233,
      "end_ts": 295.5,
      "peak_r": 1.53,
      "mean_r": 1.2244,
      "mass_r": 3.9997
    },
    {
      "start_ts": 296.633,
      "end_ts": 305.133,
      "peak_r": 1.44,
      "mean_r": 1.1211,
      "mass_r": 9.529
    },
    {
      "start_ts": 306.3,
      "end_ts": 308.433,
      "peak_r": 1.39,
      "mean_r": 1.1591,
      "mass_r": 2.4727
    },
    {
      "start_ts": 308.833,
      "end_ts": 309.633,
      "peak_r": 1.21,
      "mean_r": 1.1183,
      "mass_r": 0.8947
    },
    {
      "start_ts": 313.867,
      "end_ts": 315.5,
      "peak_r": 1.33,
      "mean_r": 1.1061,
      "mass_r": 1.8067
    },
    {
      "start_ts": 318.867,
      "end_ts": 319.4,
      "peak_r": 1.13,
      "mean_r": 1.0519,
      "mass_r": 0.561
    },
    {
      "start_ts": 319.667,
      "end_ts": 321.3,
      "peak_r": 1.32,
      "mean_r": 1.168,
      "mass_r": 1.9077
    },
    {
      "start_ts": 324.833,
      "end_ts": 326.067,
      "peak_r": 1.35,
      "mean_r": 1.1681,
      "mass_r": 1.4407
    },
    {
      "start_ts": 326.633,
      "end_ts": 331.5,
      "peak_r": 1.49,
      "mean_r": 1.2107,
      "mass_r": 5.892
    },
    {
      "start_ts": 331.967,
      "end_ts": 336.6,
      "peak_r": 1.47,
      "mean_r": 1.2257,
      "mass_r": 5.679
    },
    {
      "start_ts": 338.567,
      "end_ts": 340.167,
      "peak_r": 1.23,
      "mean_r": 1.1035,
      "mass_r": 1.7657
    },
    {
      "start_ts": 345.867,
      "end_ts": 348.267,
      "peak_r": 1.32,
      "mean_r": 1.101,
      "mass_r": 2.6423
    },
    {
      "start_ts": 358.4,
      "end_ts": 359.267,
      "peak_r": 1.33,
      "mean_r": 1.1031,
      "mass_r": 0.956
    },
    {
      "start_ts": 360.267,
      "end_ts": 360.8,
      "peak_r": 1.34,
      "mean_r": 1.13,
      "mass_r": 0.6027
    },
    {
      "start_ts": 361.167,
      "end_ts": 362.633,
      "peak_r": 1.27,
      "mean_r": 1.0861,
      "mass_r": 1.593
    },
    {
      "start_ts": 367.867,
      "end_ts": 368.4,
      "peak_r": 1.3,
      "mean_r": 1.1313,
      "mass_r": 0.6033
    },
    {
      "start_ts": 371.0,
      "end_ts": 371.5,
      "peak_r": 1.17,
      "mean_r": 1.082,
      "mass_r": 0.541
    },
    {
      "start_ts": 372.767,
      "end_ts": 377.067,
      "peak_r": 1.64,
      "mean_r": 1.1855,
      "mass_r": 5.0977
    },
    {
      "start_ts": 378.0,
      "end_ts": 379.533,
      "peak_r": 1.43,
      "mean_r": 1.2567,
      "mass_r": 1.927
    },
    {
      "start_ts": 379.7,
      "end_ts": 383.067,
      "peak_r": 1.78,
      "mean_r": 1.3888,
      "mass_r": 4.6757
    },
    {
      "start_ts": 383.467,
      "end_ts": 384.833,
      "peak_r": 1.44,
      "mean_r": 1.1822,
      "mass_r": 1.6157
    },
    {
      "start_ts": 385.067,
      "end_ts": 388.1,
      "peak_r": 1.3,
      "mean_r": 1.1224,
      "mass_r": 3.4047
    },
    {
      "start_ts": 388.633,
      "end_ts": 389.7,
      "peak_r": 1.25,
      "mean_r": 1.0984,
      "mass_r": 1.1717
    },
    {
      "start_ts": 393.633,
      "end_ts": 394.633,
      "peak_r": 1.23,
      "mean_r": 1.1403,
      "mass_r": 1.1403
    },
    {
      "start_ts": 395.1,
      "end_ts": 396.267,
      "peak_r": 1.51,
      "mean_r": 1.2097,
      "mass_r": 1.4113
    },
    {
      "start_ts": 398.433,
      "end_ts": 400.6,
      "peak_r": 1.25,
      "mean_r": 1.1171,
      "mass_r": 2.4203
    },
    {
      "start_ts": 403.267,
      "end_ts": 403.8,
      "peak_r": 1.07,
      "mean_r": 1.0312,
      "mass_r": 0.55
    },
    {
      "start_ts": 412.9,
      "end_ts": 414.133,
      "peak_r": 1.16,
      "mean_r": 1.0546,
      "mass_r": 1.3007
    },
    {
      "start_ts": 417.467,
      "end_ts": 418.4,
      "peak_r": 1.37,
      "mean_r": 1.1007,
      "mass_r": 1.0273
    },
    {
      "start_ts": 421.633,
      "end_ts": 422.167,
      "peak_r": 1.16,
      "mean_r": 1.0644,
      "mass_r": 0.5677
    },
    {
      "start_ts": 424.3,
      "end_ts": 424.833,
      "peak_r": 1.18,
      "mean_r": 1.1225,
      "mass_r": 0.5987
    },
    {
      "start_ts": 429.033,
      "end_ts": 429.8,
      "peak_r": 1.24,
      "mean_r": 1.107,
      "mass_r": 0.8487
    },
    {
      "start_ts": 434.2,
      "end_ts": 434.8,
      "peak_r": 1.19,
      "mean_r": 1.125,
      "mass_r": 0.675
    },
    {
      "start_ts": 436.633,
      "end_ts": 437.267,
      "peak_r": 1.18,
      "mean_r": 1.0716,
      "mass_r": 0.6787
    },
    {
      "start_ts": 438.7,
      "end_ts": 439.367,
      "peak_r": 1.33,
      "mean_r": 1.1715,
      "mass_r": 0.781
    },
    {
      "start_ts": 441.067,
      "end_ts": 441.8,
      "peak_r": 1.11,
      "mean_r": 1.0555,
      "mass_r": 0.774
    },
    {
      "start_ts": 444.3,
      "end_ts": 444.8,
      "peak_r": 1.25,
      "mean_r": 1.154,
      "mass_r": 0.577
    },
    {
      "start_ts": 447.167,
      "end_ts": 449.533,
      "peak_r": 1.67,
      "mean_r": 1.3039,
      "mass_r": 3.086
    },
    {
      "start_ts": 450.833,
      "end_ts": 451.467,
      "peak_r": 1.13,
      "mean_r": 1.0584,
      "mass_r": 0.6703
    },
    {
      "start_ts": 453.2,
      "end_ts": 454.0,
      "peak_r": 1.53,
      "mean_r": 1.2821,
      "mass_r": 1.0257
    },
    {
      "start_ts": 473.567,
      "end_ts": 475.9,
      "peak_r": 1.43,
      "mean_r": 1.155,
      "mass_r": 2.695
    },
    {
      "start_ts": 477.133,
      "end_ts": 478.533,
      "peak_r": 1.31,
      "mean_r": 1.121,
      "mass_r": 1.5693
    },
    {
      "start_ts": 480.5,
      "end_ts": 481.433,
      "peak_r": 1.45,
      "mean_r": 1.1704,
      "mass_r": 1.0923
    },
    {
      "start_ts": 484.767,
      "end_ts": 488.1,
      "peak_r": 1.41,
      "mean_r": 1.197,
      "mass_r": 3.99
    },
    {
      "start_ts": 488.533,
      "end_ts": 489.8,
      "peak_r": 1.2,
      "mean_r": 1.0476,
      "mass_r": 1.327
    },
    {
      "start_ts": 489.967,
      "end_ts": 490.867,
      "peak_r": 1.23,
      "mean_r": 1.1296,
      "mass_r": 1.0167
    },
    {
      "start_ts": 492.9,
      "end_ts": 493.667,
      "peak_r": 1.18,
      "mean_r": 1.1187,
      "mass_r": 0.8577
    },
    {
      "start_ts": 501.533,
      "end_ts": 502.7,
      "peak_r": 1.38,
      "mean_r": 1.1631,
      "mass_r": 1.357
    },
    {
      "start_ts": 505.5,
      "end_ts": 506.167,
      "peak_r": 1.26,
      "mean_r": 1.0785,
      "mass_r": 0.719
    },
    {
      "start_ts": 509.667,
      "end_ts": 511.267,
      "peak_r": 1.48,
      "mean_r": 1.1617,
      "mass_r": 1.8587
    },
    {
      "start_ts": 512.5,
      "end_ts": 513.0,
      "peak_r": 1.35,
      "mean_r": 1.1893,
      "mass_r": 0.5947
    },
    {
      "start_ts": 513.233,
      "end_ts": 517.5,
      "peak_r": 1.45,
      "mean_r": 1.1959,
      "mass_r": 5.1023
    },
    {
      "start_ts": 518.8,
      "end_ts": 521.3,
      "peak_r": 1.38,
      "mean_r": 1.1693,
      "mass_r": 2.9233
    },
    {
      "start_ts": 525.0,
      "end_ts": 526.933,
      "peak_r": 1.23,
      "mean_r": 1.0938,
      "mass_r": 2.1147
    },
    {
      "start_ts": 528.533,
      "end_ts": 530.167,
      "peak_r": 1.37,
      "mean_r": 1.1645,
      "mass_r": 1.902
    },
    {
      "start_ts": 530.633,
      "end_ts": 531.267,
      "peak_r": 1.29,
      "mean_r": 1.0974,
      "mass_r": 0.695
    },
    {
      "start_ts": 532.267,
      "end_ts": 533.7,
      "peak_r": 1.24,
      "mean_r": 1.0981,
      "mass_r": 1.574
    },
    {
      "start_ts": 538.333,
      "end_ts": 539.533,
      "peak_r": 1.35,
      "mean_r": 1.1483,
      "mass_r": 1.378
    },
    {
      "start_ts": 539.667,
      "end_ts": 540.367,
      "peak_r": 1.14,
      "mean_r": 1.0338,
      "mass_r": 0.7237
    },
    {
      "start_ts": 542.033,
      "end_ts": 543.233,
      "peak_r": 1.35,
      "mean_r": 1.0956,
      "mass_r": 1.3147
    },
    {
      "start_ts": 545.233,
      "end_ts": 546.733,
      "peak_r": 1.39,
      "mean_r": 1.1731,
      "mass_r": 1.7597
    },
    {
      "start_ts": 559.967,
      "end_ts": 560.7,
      "peak_r": 1.37,
      "mean_r": 1.1627,
      "mass_r": 0.8527
    },
    {
      "start_ts": 566.633,
      "end_ts": 567.3,
      "peak_r": 1.41,
      "mean_r": 1.1365,
      "mass_r": 0.7577
    },
    {
      "start_ts": 570.1,
      "end_ts": 571.367,
      "peak_r": 1.48,
      "mean_r": 1.1626,
      "mass_r": 1.4727
    },
    {
      "start_ts": 576.733,
      "end_ts": 577.633,
      "peak_r": 1.17,
      "mean_r": 1.0752,
      "mass_r": 0.9677
    },
    {
      "start_ts": 590.533,
      "end_ts": 593.967,
      "peak_r": 1.46,
      "mean_r": 1.2109,
      "mass_r": 4.1573
    },
    {
      "start_ts": 595.233,
      "end_ts": 596.633,
      "peak_r": 1.41,
      "mean_r": 1.2431,
      "mass_r": 1.7403
    },
    {
      "start_ts": 596.8,
      "end_ts": 597.867,
      "peak_r": 1.29,
      "mean_r": 1.1659,
      "mass_r": 1.2437
    },
    {
      "start_ts": 598.2,
      "end_ts": 599.133,
      "peak_r": 1.3,
      "mean_r": 1.1304,
      "mass_r": 1.055
    },
    {
      "start_ts": 600.033,
      "end_ts": 602.533,
      "peak_r": 1.27,
      "mean_r": 1.1203,
      "mass_r": 2.8007
    },
    {
      "start_ts": 603.233,
      "end_ts": 603.967,
      "peak_r": 1.25,
      "mean_r": 1.1145,
      "mass_r": 0.8173
    },
    {
      "start_ts": 606.5,
      "end_ts": 608.033,
      "peak_r": 1.56,
      "mean_r": 1.2452,
      "mass_r": 1.9093
    },
    {
      "start_ts": 610.233,
      "end_ts": 610.867,
      "peak_r": 1.11,
      "mean_r": 1.0516,
      "mass_r": 0.666
    },
    {
      "start_ts": 612.8,
      "end_ts": 613.733,
      "peak_r": 1.33,
      "mean_r": 1.155,
      "mass_r": 1.078
    },
    {
      "start_ts": 615.767,
      "end_ts": 616.933,
      "peak_r": 1.43,
      "mean_r": 1.2283,
      "mass_r": 1.433
    },
    {
      "start_ts": 619.533,
      "end_ts": 620.4,
      "peak_r": 1.38,
      "mean_r": 1.1415,
      "mass_r": 0.9893
    },
    {
      "start_ts": 621.833,
      "end_ts": 624.167,
      "peak_r": 1.61,
      "mean_r": 1.1587,
      "mass_r": 2.7037
    },
    {
      "start_ts": 630.6,
      "end_ts": 631.467,
      "peak_r": 1.15,
      "mean_r": 1.065,
      "mass_r": 0.923
    },
    {
      "start_ts": 633.633,
      "end_ts": 635.9,
      "peak_r": 1.97,
      "mean_r": 1.6007,
      "mass_r": 3.6283
    },
    {
      "start_ts": 639.5,
      "end_ts": 641.867,
      "peak_r": 1.48,
      "mean_r": 1.2585,
      "mass_r": 2.9783
    },
    {
      "start_ts": 644.833,
      "end_ts": 645.867,
      "peak_r": 1.22,
      "mean_r": 1.1071,
      "mass_r": 1.144
    },
    {
      "start_ts": 655.5,
      "end_ts": 656.067,
      "peak_r": 1.28,
      "mean_r": 1.1541,
      "mass_r": 0.654
    },
    {
      "start_ts": 659.167,
      "end_ts": 660.133,
      "peak_r": 1.2,
      "mean_r": 1.1186,
      "mass_r": 1.0813
    },
    {
      "start_ts": 667.7,
      "end_ts": 668.8,
      "peak_r": 1.37,
      "mean_r": 1.1785,
      "mass_r": 1.2963
    },
    {
      "start_ts": 669.233,
      "end_ts": 670.433,
      "peak_r": 1.55,
      "mean_r": 1.1819,
      "mass_r": 1.4183
    },
    {
      "start_ts": 670.967,
      "end_ts": 675.133,
      "peak_r": 1.47,
      "mean_r": 1.2324,
      "mass_r": 5.135
    },
    {
      "start_ts": 675.8,
      "end_ts": 683.233,
      "peak_r": 1.74,
      "mean_r": 1.308,
      "mass_r": 9.723
    },
    {
      "start_ts": 683.533,
      "end_ts": 695.633,
      "peak_r": 1.85,
      "mean_r": 1.4643,
      "mass_r": 17.7183
    },
    {
      "start_ts": 695.9,
      "end_ts": 697.033,
      "peak_r": 1.46,
      "mean_r": 1.2003,
      "mass_r": 1.3603
    },
    {
      "start_ts": 697.733,
      "end_ts": 700.833,
      "peak_r": 1.59,
      "mean_r": 1.2524,
      "mass_r": 3.8823
    },
    {
      "start_ts": 701.133,
      "end_ts": 702.567,
      "peak_r": 1.28,
      "mean_r": 1.1447,
      "mass_r": 1.6407
    },
    {
      "start_ts": 705.6,
      "end_ts": 706.333,
      "peak_r": 1.17,
      "mean_r": 1.0314,
      "mass_r": 0.7563
    },
    {
      "start_ts": 707.433,
      "end_ts": 708.167,
      "peak_r": 1.22,
      "mean_r": 1.0891,
      "mass_r": 0.7987
    },
    {
      "start_ts": 712.6,
      "end_ts": 715.433,
      "peak_r": 1.58,
      "mean_r": 1.3046,
      "mass_r": 3.6963
    },
    {
      "start_ts": 717.233,
      "end_ts": 718.633,
      "peak_r": 1.25,
      "mean_r": 1.135,
      "mass_r": 1.589
    },
    {
      "start_ts": 719.467,
      "end_ts": 720.767,
      "peak_r": 1.34,
      "mean_r": 1.1641,
      "mass_r": 1.5133
    },
    {
      "start_ts": 724.067,
      "end_ts": 724.633,
      "peak_r": 1.26,
      "mean_r": 1.1224,
      "mass_r": 0.636
    },
    {
      "start_ts": 725.167,
      "end_ts": 725.8,
      "peak_r": 1.23,
      "mean_r": 1.1595,
      "mass_r": 0.7343
    },
    {
      "start_ts": 729.033,
      "end_ts": 730.8,
      "peak_r": 1.44,
      "mean_r": 1.1879,
      "mass_r": 2.0987
    },
    {
      "start_ts": 731.167,
      "end_ts": 733.033,
      "peak_r": 1.32,
      "mean_r": 1.1277,
      "mass_r": 2.105
    },
    {
      "start_ts": 733.467,
      "end_ts": 734.133,
      "peak_r": 1.33,
      "mean_r": 1.2185,
      "mass_r": 0.8123
    },
    {
      "start_ts": 736.733,
      "end_ts": 738.733,
      "peak_r": 1.33,
      "mean_r": 1.1602,
      "mass_r": 2.3203
    },
    {
      "start_ts": 739.4,
      "end_ts": 741.067,
      "peak_r": 1.38,
      "mean_r": 1.1506,
      "mass_r": 1.9177
    },
    {
      "start_ts": 741.967,
      "end_ts": 742.633,
      "peak_r": 1.09,
      "mean_r": 1.0305,
      "mass_r": 0.687
    },
    {
      "start_ts": 743.0,
      "end_ts": 746.167,
      "peak_r": 1.49,
      "mean_r": 1.2545,
      "mass_r": 3.9727
    },
    {
      "start_ts": 747.233,
      "end_ts": 748.7,
      "peak_r": 1.27,
      "mean_r": 1.1527,
      "mass_r": 1.6907
    },
    {
      "start_ts": 753.567,
      "end_ts": 757.8,
      "peak_r": 1.53,
      "mean_r": 1.2963,
      "mass_r": 5.4877
    },
    {
      "start_ts": 758.733,
      "end_ts": 760.433,
      "peak_r": 1.29,
      "mean_r": 1.1045,
      "mass_r": 1.8777
    },
    {
      "start_ts": 761.067,
      "end_ts": 771.4,
      "peak_r": 2.08,
      "mean_r": 1.2903,
      "mass_r": 13.3333
    },
    {
      "start_ts": 771.533,
      "end_ts": 774.933,
      "peak_r": 2.37,
      "mean_r": 1.3665,
      "mass_r": 4.646
    },
    {
      "start_ts": 777.433,
      "end_ts": 778.0,
      "peak_r": 1.08,
      "mean_r": 1.0335,
      "mass_r": 0.5857
    },
    {
      "start_ts": 781.333,
      "end_ts": 783.833,
      "peak_r": 1.47,
      "mean_r": 1.1909,
      "mass_r": 2.9773
    },
    {
      "start_ts": 784.533,
      "end_ts": 786.1,
      "peak_r": 1.38,
      "mean_r": 1.2051,
      "mass_r": 1.888
    },
    {
      "start_ts": 786.5,
      "end_ts": 787.0,
      "peak_r": 1.24,
      "mean_r": 1.1287,
      "mass_r": 0.5643
    },
    {
      "start_ts": 788.067,
      "end_ts": 789.933,
      "peak_r": 1.46,
      "mean_r": 1.2354,
      "mass_r": 2.306
    },
    {
      "start_ts": 791.367,
      "end_ts": 792.233,
      "peak_r": 1.21,
      "mean_r": 1.1215,
      "mass_r": 0.972
    },
    {
      "start_ts": 793.8,
      "end_ts": 794.367,
      "peak_r": 1.18,
      "mean_r": 1.0865,
      "mass_r": 0.6157
    },
    {
      "start_ts": 794.567,
      "end_ts": 795.633,
      "peak_r": 1.42,
      "mean_r": 1.0862,
      "mass_r": 1.1587
    },
    {
      "start_ts": 797.933,
      "end_ts": 802.1,
      "peak_r": 1.32,
      "mean_r": 1.1129,
      "mass_r": 4.637
    },
    {
      "start_ts": 803.233,
      "end_ts": 803.833,
      "peak_r": 1.19,
      "mean_r": 1.1278,
      "mass_r": 0.6767
    },
    {
      "start_ts": 804.333,
      "end_ts": 809.833,
      "peak_r": 1.53,
      "mean_r": 1.1759,
      "mass_r": 6.4673
    },
    {
      "start_ts": 810.967,
      "end_ts": 813.4,
      "peak_r": 1.37,
      "mean_r": 1.1605,
      "mass_r": 2.824
    },
    {
      "start_ts": 814.367,
      "end_ts": 818.633,
      "peak_r": 1.48,
      "mean_r": 1.1682,
      "mass_r": 4.9843
    },
    {
      "start_ts": 827.367,
      "end_ts": 833.0,
      "peak_r": 1.84,
      "mean_r": 1.2757,
      "mass_r": 7.1867
    },
    {
      "start_ts": 833.633,
      "end_ts": 836.433,
      "peak_r": 1.43,
      "mean_r": 1.1963,
      "mass_r": 3.3497
    },
    {
      "start_ts": 838.533,
      "end_ts": 839.067,
      "peak_r": 1.16,
      "mean_r": 1.0688,
      "mass_r": 0.57
    },
    {
      "start_ts": 840.0,
      "end_ts": 845.033,
      "peak_r": 1.45,
      "mean_r": 1.1919,
      "mass_r": 5.9993
    },
    {
      "start_ts": 845.5,
      "end_ts": 846.3,
      "peak_r": 1.54,
      "mean_r": 1.2533,
      "mass_r": 1.0027
    },
    {
      "start_ts": 846.667,
      "end_ts": 849.5,
      "peak_r": 1.52,
      "mean_r": 1.1634,
      "mass_r": 3.2963
    },
    {
      "start_ts": 849.933,
      "end_ts": 852.1,
      "peak_r": 1.32,
      "mean_r": 1.1609,
      "mass_r": 2.5153
    },
    {
      "start_ts": 852.7,
      "end_ts": 858.0,
      "peak_r": 1.75,
      "mean_r": 1.2379,
      "mass_r": 6.561
    },
    {
      "start_ts": 860.033,
      "end_ts": 861.9,
      "peak_r": 1.29,
      "mean_r": 1.1384,
      "mass_r": 2.125
    },
    {
      "start_ts": 867.133,
      "end_ts": 867.767,
      "peak_r": 1.11,
      "mean_r": 1.0258,
      "mass_r": 0.6497
    },
    {
      "start_ts": 868.2,
      "end_ts": 869.5,
      "peak_r": 1.41,
      "mean_r": 1.1372,
      "mass_r": 1.4783
    },
    {
      "start_ts": 869.833,
      "end_ts": 873.9,
      "peak_r": 1.68,
      "mean_r": 1.2889,
      "mass_r": 5.2417
    },
    {
      "start_ts": 873.967,
      "end_ts": 884.033,
      "peak_r": 1.5,
      "mean_r": 1.1688,
      "mass_r": 11.7657
    },
    {
      "start_ts": 885.2,
      "end_ts": 891.867,
      "peak_r": 1.46,
      "mean_r": 1.2064,
      "mass_r": 8.0423
    },
    {
      "start_ts": 893.9,
      "end_ts": 897.4,
      "peak_r": 1.61,
      "mean_r": 1.2878,
      "mass_r": 4.5073
    },
    {
      "start_ts": 897.667,
      "end_ts": 901.567,
      "peak_r": 1.64,
      "mean_r": 1.2504,
      "mass_r": 4.8767
    },
    {
      "start_ts": 901.833,
      "end_ts": 923.867,
      "peak_r": 1.84,
      "mean_r": 1.3607,
      "mass_r": 29.9797
    },
    {
      "start_ts": 924.333,
      "end_ts": 925.333,
      "peak_r": 1.24,
      "mean_r": 1.0667,
      "mass_r": 1.0667
    },
    {
      "start_ts": 926.2,
      "end_ts": 929.967,
      "peak_r": 1.42,
      "mean_r": 1.1687,
      "mass_r": 4.402
    },
    {
      "start_ts": 930.033,
      "end_ts": 934.7,
      "peak_r": 1.51,
      "mean_r": 1.2098,
      "mass_r": 5.6457
    },
    {
      "start_ts": 936.267,
      "end_ts": 937.067,
      "peak_r": 1.27,
      "mean_r": 1.1592,
      "mass_r": 0.9273
    },
    {
      "start_ts": 937.667,
      "end_ts": 938.5,
      "peak_r": 1.35,
      "mean_r": 1.1476,
      "mass_r": 0.9563
    },
    {
      "start_ts": 938.733,
      "end_ts": 939.667,
      "peak_r": 1.32,
      "mean_r": 1.1761,
      "mass_r": 1.0977
    },
    {
      "start_ts": 941.233,
      "end_ts": 950.6,
      "peak_r": 1.49,
      "mean_r": 1.1806,
      "mass_r": 11.0587
    },
    {
      "start_ts": 950.967,
      "end_ts": 953.7,
      "peak_r": 1.56,
      "mean_r": 1.283,
      "mass_r": 3.507
    },
    {
      "start_ts": 954.1,
      "end_ts": 958.433,
      "peak_r": 1.45,
      "mean_r": 1.2023,
      "mass_r": 5.21
    },
    {
      "start_ts": 959.5,
      "end_ts": 965.133,
      "peak_r": 1.75,
      "mean_r": 1.3378,
      "mass_r": 7.5363
    },
    {
      "start_ts": 965.267,
      "end_ts": 970.533,
      "peak_r": 1.67,
      "mean_r": 1.3016,
      "mass_r": 6.855
    },
    {
      "start_ts": 970.633,
      "end_ts": 971.133,
      "peak_r": 1.24,
      "mean_r": 1.1233,
      "mass_r": 0.5617
    },
    {
      "start_ts": 971.5,
      "end_ts": 975.967,
      "peak_r": 1.54,
      "mean_r": 1.2943,
      "mass_r": 5.781
    },
    {
      "start_ts": 976.0,
      "end_ts": 981.1,
      "peak_r": 1.5,
      "mean_r": 1.2342,
      "mass_r": 6.2947
    },
    {
      "start_ts": 981.5,
      "end_ts": 986.033,
      "peak_r": 1.66,
      "mean_r": 1.2231,
      "mass_r": 5.5447
    },
    {
      "start_ts": 986.567,
      "end_ts": 995.7,
      "peak_r": 1.55,
      "mean_r": 1.2593,
      "mass_r": 11.502
    },
    {
      "start_ts": 996.533,
      "end_ts": 1000.333,
      "peak_r": 1.64,
      "mean_r": 1.2965,
      "mass_r": 4.9267
    },
    {
      "start_ts": 1001.0,
      "end_ts": 1002.167,
      "peak_r": 1.19,
      "mean_r": 1.0914,
      "mass_r": 1.2733
    },
    {
      "start_ts": 1002.4,
      "end_ts": 1003.833,
      "peak_r": 1.4,
      "mean_r": 1.1656,
      "mass_r": 1.6707
    },
    {
      "start_ts": 1007.567,
      "end_ts": 1008.667,
      "peak_r": 1.45,
      "mean_r": 1.2385,
      "mass_r": 1.3623
    },
    {
      "start_ts": 1008.933,
      "end_ts": 1010.067,
      "peak_r": 1.33,
      "mean_r": 1.1482,
      "mass_r": 1.3013
    },
    {
      "start_ts": 1011.3,
      "end_ts": 1012.0,
      "peak_r": 1.15,
      "mean_r": 1.09,
      "mass_r": 0.763
    },
    {
      "start_ts": 1014.6,
      "end_ts": 1016.5,
      "peak_r": 1.35,
      "mean_r": 1.1614,
      "mass_r": 2.2067
    },
    {
      "start_ts": 1016.633,
      "end_ts": 1018.667,
      "peak_r": 1.31,
      "mean_r": 1.1205,
      "mass_r": 2.2783
    },
    {
      "start_ts": 1018.867,
      "end_ts": 1020.167,
      "peak_r": 1.42,
      "mean_r": 1.1136,
      "mass_r": 1.4477
    },
    {
      "start_ts": 1020.5,
      "end_ts": 1046.1,
      "peak_r": 2.37,
      "mean_r": 1.5929,
      "mass_r": 40.779
    },
    {
      "start_ts": 1050.5,
      "end_ts": 1052.533,
      "peak_r": 1.4,
      "mean_r": 1.1561,
      "mass_r": 2.3507
    },
    {
      "start_ts": 1053.333,
      "end_ts": 1072.8,
      "peak_r": 2.09,
      "mean_r": 1.5361,
      "mass_r": 29.903
    },
    {
      "start_ts": 1077.5,
      "end_ts": 1079.767,
      "peak_r": 1.72,
      "mean_r": 1.3671,
      "mass_r": 3.0987
    },
    {
      "start_ts": 1079.833,
      "end_ts": 1093.033,
      "peak_r": 1.9,
      "mean_r": 1.3042,
      "mass_r": 17.2157
    },
    {
      "start_ts": 1093.4,
      "end_ts": 1096.533,
      "peak_r": 1.41,
      "mean_r": 1.1368,
      "mass_r": 3.562
    },
    {
      "start_ts": 1096.7,
      "end_ts": 1109.9,
      "peak_r": 2.2,
      "mean_r": 1.5302,
      "mass_r": 20.198
    },
    {
      "start_ts": 1110.567,
      "end_ts": 1129.433,
      "peak_r": 2.06,
      "mean_r": 1.4691,
      "mass_r": 27.7163
    },
    {
      "start_ts": 1129.6,
      "end_ts": 1135.067,
      "peak_r": 1.99,
      "mean_r": 1.4796,
      "mass_r": 8.0883
    },
    {
      "start_ts": 1136.033,
      "end_ts": 1136.567,
      "peak_r": 1.13,
      "mean_r": 1.0844,
      "mass_r": 0.5783
    },
    {
      "start_ts": 1138.8,
      "end_ts": 1140.167,
      "peak_r": 1.11,
      "mean_r": 1.0393,
      "mass_r": 1.4203
    },
    {
      "start_ts": 1143.6,
      "end_ts": 1144.2,
      "peak_r": 1.16,
      "mean_r": 1.055,
      "mass_r": 0.633
    },
    {
      "start_ts": 1144.433,
      "end_ts": 1150.033,
      "peak_r": 1.6,
      "mean_r": 1.2779,
      "mass_r": 7.156
    },
    {
      "start_ts": 1151.033,
      "end_ts": 1152.233,
      "peak_r": 1.41,
      "mean_r": 1.1664,
      "mass_r": 1.3997
    },
    {
      "start_ts": 1153.533,
      "end_ts": 1154.2,
      "peak_r": 1.23,
      "mean_r": 1.1155,
      "mass_r": 0.7437
    },
    {
      "start_ts": 1154.533,
      "end_ts": 1156.233,
      "peak_r": 1.29,
      "mean_r": 1.1276,
      "mass_r": 1.917
    },
    {
      "start_ts": 1156.6,
      "end_ts": 1157.5,
      "peak_r": 1.33,
      "mean_r": 1.1711,
      "mass_r": 1.054
    },
    {
      "start_ts": 1157.7,
      "end_ts": 1161.5,
      "peak_r": 1.57,
      "mean_r": 1.2473,
      "mass_r": 4.7397
    },
    {
      "start_ts": 1161.8,
      "end_ts": 1163.5,
      "peak_r": 1.46,
      "mean_r": 1.188,
      "mass_r": 2.0197
    },
    {
      "start_ts": 1165.367,
      "end_ts": 1174.0,
      "peak_r": 1.78,
      "mean_r": 1.3355,
      "mass_r": 11.53
    },
    {
      "start_ts": 1174.533,
      "end_ts": 1178.333,
      "peak_r": 1.61,
      "mean_r": 1.3248,
      "mass_r": 5.0343
    },
    {
      "start_ts": 1178.667,
      "end_ts": 1187.267,
      "peak_r": 1.75,
      "mean_r": 1.304,
      "mass_r": 11.2147
    },
    {
      "start_ts": 1187.733,
      "end_ts": 1188.233,
      "peak_r": 1.22,
      "mean_r": 1.138,
      "mass_r": 0.569
    },
    {
      "start_ts": 1192.0,
      "end_ts": 1192.767,
      "peak_r": 1.2,
      "mean_r": 1.1052,
      "mass_r": 0.8473
    },
    {
      "start_ts": 1192.933,
      "end_ts": 1195.433,
      "peak_r": 1.52,
      "mean_r": 1.1981,
      "mass_r": 2.9953
    },
    {
      "start_ts": 1195.5,
      "end_ts": 1196.733,
      "peak_r": 1.27,
      "mean_r": 1.1473,
      "mass_r": 1.415
    },
    {
      "start_ts": 1197.467,
      "end_ts": 1200.9,
      "peak_r": 1.55,
      "mean_r": 1.2802,
      "mass_r": 4.3953
    },
    {
      "start_ts": 1201.333,
      "end_ts": 1202.967,
      "peak_r": 1.36,
      "mean_r": 1.1394,
      "mass_r": 1.861
    },
    {
      "start_ts": 1204.4,
      "end_ts": 1205.167,
      "peak_r": 1.07,
      "mean_r": 1.0278,
      "mass_r": 0.788
    },
    {
      "start_ts": 1206.3,
      "end_ts": 1207.5,
      "peak_r": 1.46,
      "mean_r": 1.2422,
      "mass_r": 1.4907
    },
    {
      "start_ts": 1208.4,
      "end_ts": 1216.567,
      "peak_r": 1.87,
      "mean_r": 1.342,
      "mass_r": 10.9593
    },
    {
      "start_ts": 1216.633,
      "end_ts": 1237.433,
      "peak_r": 2.19,
      "mean_r": 1.4918,
      "mass_r": 31.0303
    },
    {
      "start_ts": 1237.7,
      "end_ts": 1240.7,
      "peak_r": 1.67,
      "mean_r": 1.3139,
      "mass_r": 3.9417
    },
    {
      "start_ts": 1241.0,
      "end_ts": 1242.067,
      "peak_r": 1.34,
      "mean_r": 1.1812,
      "mass_r": 1.26
    },
    {
      "start_ts": 1242.433,
      "end_ts": 1258.7,
      "peak_r": 1.86,
      "mean_r": 1.2767,
      "mass_r": 20.768
    },
    {
      "start_ts": 1260.033,
      "end_ts": 1262.933,
      "peak_r": 1.5,
      "mean_r": 1.218,
      "mass_r": 3.5323
    },
    {
      "start_ts": 1264.5,
      "end_ts": 1266.967,
      "peak_r": 1.54,
      "mean_r": 1.14,
      "mass_r": 2.812
    },
    {
      "start_ts": 1267.133,
      "end_ts": 1269.367,
      "peak_r": 1.65,
      "mean_r": 1.1688,
      "mass_r": 2.6103
    },
    {
      "start_ts": 1269.733,
      "end_ts": 1270.567,
      "peak_r": 1.28,
      "mean_r": 1.1212,
      "mass_r": 0.9343
    },
    {
      "start_ts": 1271.0,
      "end_ts": 1271.933,
      "peak_r": 1.25,
      "mean_r": 1.0946,
      "mass_r": 1.0217
    },
    {
      "start_ts": 1272.267,
      "end_ts": 1277.6,
      "peak_r": 1.55,
      "mean_r": 1.2482,
      "mass_r": 6.657
    },
    {
      "start_ts": 1277.967,
      "end_ts": 1281.167,
      "peak_r": 1.47,
      "mean_r": 1.2386,
      "mass_r": 3.9637
    },
    {
      "start_ts": 1281.333,
      "end_ts": 1286.2,
      "peak_r": 1.63,
      "mean_r": 1.2932,
      "mass_r": 6.2933
    },
    {
      "start_ts": 1286.967,
      "end_ts": 1287.5,
      "peak_r": 1.15,
      "mean_r": 1.0956,
      "mass_r": 0.5843
    },
    {
      "start_ts": 1287.967,
      "end_ts": 1291.467,
      "peak_r": 1.58,
      "mean_r": 1.2991,
      "mass_r": 4.547
    },
    {
      "start_ts": 1292.167,
      "end_ts": 1295.3,
      "peak_r": 1.57,
      "mean_r": 1.1968,
      "mass_r": 3.75
    },
    {
      "start_ts": 1295.9,
      "end_ts": 1298.233,
      "peak_r": 1.44,
      "mean_r": 1.1754,
      "mass_r": 2.7427
    },
    {
      "start_ts": 1298.7,
      "end_ts": 1300.0,
      "peak_r": 1.22,
      "mean_r": 1.1046,
      "mass_r": 1.436
    },
    {
      "start_ts": 1300.1,
      "end_ts": 1300.8,
      "peak_r": 1.27,
      "mean_r": 1.17,
      "mass_r": 0.819
    },
    {
      "start_ts": 1303.033,
      "end_ts": 1303.733,
      "peak_r": 1.23,
      "mean_r": 1.1086,
      "mass_r": 0.776
    },
    {
      "start_ts": 1304.8,
      "end_ts": 1309.533,
      "peak_r": 1.57,
      "mean_r": 1.2203,
      "mass_r": 5.776
    },
    {
      "start_ts": 1310.533,
      "end_ts": 1311.467,
      "peak_r": 1.18,
      "mean_r": 1.0932,
      "mass_r": 1.0203
    },
    {
      "start_ts": 1311.833,
      "end_ts": 1313.7,
      "peak_r": 1.36,
      "mean_r": 1.1282,
      "mass_r": 2.106
    },
    {
      "start_ts": 1314.367,
      "end_ts": 1315.1,
      "peak_r": 1.27,
      "mean_r": 1.135,
      "mass_r": 0.8323
    },
    {
      "start_ts": 1316.167,
      "end_ts": 1317.833,
      "peak_r": 1.42,
      "mean_r": 1.1646,
      "mass_r": 1.941
    },
    {
      "start_ts": 1319.933,
      "end_ts": 1321.867,
      "peak_r": 1.33,
      "mean_r": 1.1816,
      "mass_r": 2.2843
    },
    {
      "start_ts": 1322.3,
      "end_ts": 1322.833,
      "peak_r": 1.11,
      "mean_r": 1.0369,
      "mass_r": 0.553
    },
    {
      "start_ts": 1323.433,
      "end_ts": 1325.467,
      "peak_r": 1.53,
      "mean_r": 1.2759,
      "mass_r": 2.5943
    },
    {
      "start_ts": 1326.267,
      "end_ts": 1328.667,
      "peak_r": 1.46,
      "mean_r": 1.2611,
      "mass_r": 3.0267
    },
    {
      "start_ts": 1329.167,
      "end_ts": 1330.067,
      "peak_r": 1.35,
      "mean_r": 1.2226,
      "mass_r": 1.1003
    },
    {
      "start_ts": 1330.433,
      "end_ts": 1331.967,
      "peak_r": 1.73,
      "mean_r": 1.3054,
      "mass_r": 2.0017
    },
    {
      "start_ts": 1332.233,
      "end_ts": 1333.567,
      "peak_r": 1.53,
      "mean_r": 1.2898,
      "mass_r": 1.7197
    },
    {
      "start_ts": 1333.833,
      "end_ts": 1335.567,
      "peak_r": 1.59,
      "mean_r": 1.2077,
      "mass_r": 2.0933
    },
    {
      "start_ts": 1335.933,
      "end_ts": 1336.667,
      "peak_r": 1.27,
      "mean_r": 1.0918,
      "mass_r": 0.8007
    },
    {
      "start_ts": 1337.433,
      "end_ts": 1340.9,
      "peak_r": 1.53,
      "mean_r": 1.2178,
      "mass_r": 4.2217
    },
    {
      "start_ts": 1346.1,
      "end_ts": 1347.2,
      "peak_r": 1.63,
      "mean_r": 1.3579,
      "mass_r": 1.4937
    },
    {
      "start_ts": 1348.6,
      "end_ts": 1357.267,
      "peak_r": 1.71,
      "mean_r": 1.2909,
      "mass_r": 11.1877
    },
    {
      "start_ts": 1357.633,
      "end_ts": 1359.733,
      "peak_r": 1.42,
      "mean_r": 1.16,
      "mass_r": 2.436
    },
    {
      "start_ts": 1360.733,
      "end_ts": 1364.967,
      "peak_r": 1.61,
      "mean_r": 1.2555,
      "mass_r": 5.315
    },
    {
      "start_ts": 1365.3,
      "end_ts": 1366.0,
      "peak_r": 1.47,
      "mean_r": 1.2667,
      "mass_r": 0.8867
    },
    {
      "start_ts": 1367.567,
      "end_ts": 1372.567,
      "peak_r": 1.75,
      "mean_r": 1.2331,
      "mass_r": 6.1657
    },
    {
      "start_ts": 1372.7,
      "end_ts": 1376.533,
      "peak_r": 1.92,
      "mean_r": 1.423,
      "mass_r": 5.455
    },
    {
      "start_ts": 1376.867,
      "end_ts": 1383.667,
      "peak_r": 1.9,
      "mean_r": 1.393,
      "mass_r": 9.4727
    },
    {
      "start_ts": 1386.033,
      "end_ts": 1386.733,
      "peak_r": 1.12,
      "mean_r": 1.0648,
      "mass_r": 0.7453
    },
    {
      "start_ts": 1387.467,
      "end_ts": 1388.8,
      "peak_r": 1.42,
      "mean_r": 1.2372,
      "mass_r": 1.6497
    },
    {
      "start_ts": 1390.767,
      "end_ts": 1391.5,
      "peak_r": 1.29,
      "mean_r": 1.1345,
      "mass_r": 0.832
    },
    {
      "start_ts": 1392.767,
      "end_ts": 1393.667,
      "peak_r": 1.26,
      "mean_r": 1.1415,
      "mass_r": 1.0273
    },
    {
      "start_ts": 1394.1,
      "end_ts": 1397.2,
      "peak_r": 1.37,
      "mean_r": 1.1602,
      "mass_r": 3.5967
    },
    {
      "start_ts": 1397.267,
      "end_ts": 1399.267,
      "peak_r": 1.31,
      "mean_r": 1.1407,
      "mass_r": 2.2813
    },
    {
      "start_ts": 1400.467,
      "end_ts": 1402.667,
      "peak_r": 1.56,
      "mean_r": 1.2344,
      "mass_r": 2.7157
    },
    {
      "start_ts": 1403.4,
      "end_ts": 1404.567,
      "peak_r": 1.32,
      "mean_r": 1.1514,
      "mass_r": 1.3433
    },
    {
      "start_ts": 1405.067,
      "end_ts": 1409.367,
      "peak_r": 1.46,
      "mean_r": 1.2009,
      "mass_r": 5.164
    },
    {
      "start_ts": 1410.533,
      "end_ts": 1411.6,
      "peak_r": 1.38,
      "mean_r": 1.2081,
      "mass_r": 1.2887
    },
    {
      "start_ts": 1413.467,
      "end_ts": 1444.467,
      "peak_r": 1.86,
      "mean_r": 1.3412,
      "mass_r": 41.5777
    },
    {
      "start_ts": 1445.167,
      "end_ts": 1451.5,
      "peak_r": 2.01,
      "mean_r": 1.4337,
      "mass_r": 9.0803
    },
    {
      "start_ts": 1452.567,
      "end_ts": 1456.0,
      "peak_r": 1.52,
      "mean_r": 1.2438,
      "mass_r": 4.2703
    },
    {
      "start_ts": 1456.5,
      "end_ts": 1458.467,
      "peak_r": 1.31,
      "mean_r": 1.1563,
      "mass_r": 2.274
    },
    {
      "start_ts": 1460.9,
      "end_ts": 1463.5,
      "peak_r": 1.64,
      "mean_r": 1.2551,
      "mass_r": 3.2633
    },
    {
      "start_ts": 1464.5,
      "end_ts": 1474.033,
      "peak_r": 1.61,
      "mean_r": 1.1709,
      "mass_r": 11.1627
    },
    {
      "start_ts": 1474.533,
      "end_ts": 1475.533,
      "peak_r": 1.62,
      "mean_r": 1.22,
      "mass_r": 1.22
    },
    {
      "start_ts": 1475.8,
      "end_ts": 1477.3,
      "peak_r": 1.55,
      "mean_r": 1.2433,
      "mass_r": 1.865
    },
    {
      "start_ts": 1479.067,
      "end_ts": 1479.7,
      "peak_r": 1.42,
      "mean_r": 1.2653,
      "mass_r": 0.8013
    },
    {
      "start_ts": 1480.767,
      "end_ts": 1482.233,
      "peak_r": 1.26,
      "mean_r": 1.1445,
      "mass_r": 1.6787
    },
    {
      "start_ts": 1484.8,
      "end_ts": 1486.9,
      "peak_r": 1.44,
      "mean_r": 1.2176,
      "mass_r": 2.557
    },
    {
      "start_ts": 1487.567,
      "end_ts": 1493.5,
      "peak_r": 1.64,
      "mean_r": 1.269,
      "mass_r": 7.5293
    },
    {
      "start_ts": 1493.867,
      "end_ts": 1494.8,
      "peak_r": 1.33,
      "mean_r": 1.0782,
      "mass_r": 1.0063
    },
    {
      "start_ts": 1494.967,
      "end_ts": 1502.5,
      "peak_r": 1.76,
      "mean_r": 1.3124,
      "mass_r": 9.8867
    },
    {
      "start_ts": 1502.867,
      "end_ts": 1506.8,
      "peak_r": 1.41,
      "mean_r": 1.1216,
      "mass_r": 4.4117
    },
    {
      "start_ts": 1509.667,
      "end_ts": 1510.833,
      "peak_r": 1.17,
      "mean_r": 1.0774,
      "mass_r": 1.257
    },
    {
      "start_ts": 1511.433,
      "end_ts": 1512.0,
      "peak_r": 1.21,
      "mean_r": 1.0871,
      "mass_r": 0.616
    },
    {
      "start_ts": 1512.133,
      "end_ts": 1513.267,
      "peak_r": 1.35,
      "mean_r": 1.1806,
      "mass_r": 1.338
    },
    {
      "start_ts": 1514.467,
      "end_ts": 1515.233,
      "peak_r": 1.28,
      "mean_r": 1.1348,
      "mass_r": 0.87
    },
    {
      "start_ts": 1516.133,
      "end_ts": 1517.067,
      "peak_r": 1.38,
      "mean_r": 1.1564,
      "mass_r": 1.0793
    },
    {
      "start_ts": 1518.167,
      "end_ts": 1519.1,
      "peak_r": 1.61,
      "mean_r": 1.3104,
      "mass_r": 1.223
    },
    {
      "start_ts": 1519.4,
      "end_ts": 1525.567,
      "peak_r": 1.79,
      "mean_r": 1.2948,
      "mass_r": 7.9847
    },
    {
      "start_ts": 1525.867,
      "end_ts": 1534.9,
      "peak_r": 1.62,
      "mean_r": 1.2646,
      "mass_r": 11.424
    },
    {
      "start_ts": 1536.0,
      "end_ts": 1537.1,
      "peak_r": 1.3,
      "mean_r": 1.2042,
      "mass_r": 1.3247
    },
    {
      "start_ts": 1538.2,
      "end_ts": 1546.167,
      "peak_r": 1.68,
      "mean_r": 1.3105,
      "mass_r": 10.4403
    },
    {
      "start_ts": 1548.167,
      "end_ts": 1550.233,
      "peak_r": 1.51,
      "mean_r": 1.2189,
      "mass_r": 2.519
    },
    {
      "start_ts": 1550.933,
      "end_ts": 1552.067,
      "peak_r": 1.25,
      "mean_r": 1.1491,
      "mass_r": 1.3023
    },
    {
      "start_ts": 1552.833,
      "end_ts": 1557.033,
      "peak_r": 1.65,
      "mean_r": 1.2233,
      "mass_r": 5.138
    },
    {
      "start_ts": 1557.633,
      "end_ts": 1558.167,
      "peak_r": 1.07,
      "mean_r": 1.0106,
      "mass_r": 0.539
    },
    {
      "start_ts": 1558.833,
      "end_ts": 1564.733,
      "peak_r": 1.74,
      "mean_r": 1.2794,
      "mass_r": 7.5487
    },
    {
      "start_ts": 1567.0,
      "end_ts": 1567.567,
      "peak_r": 1.21,
      "mean_r": 1.1129,
      "mass_r": 0.6307
    },
    {
      "start_ts": 1569.5,
      "end_ts": 1570.433,
      "peak_r": 1.44,
      "mean_r": 1.2504,
      "mass_r": 1.167
    },
    {
      "start_ts": 1570.567,
      "end_ts": 1577.2,
      "peak_r": 2.05,
      "mean_r": 1.4791,
      "mass_r": 9.8117
    },
    {
      "start_ts": 1577.833,
      "end_ts": 1579.433,
      "peak_r": 1.42,
      "mean_r": 1.1977,
      "mass_r": 1.9163
    },
    {
      "start_ts": 1579.833,
      "end_ts": 1580.333,
      "peak_r": 1.3,
      "mean_r": 1.1813,
      "mass_r": 0.5907
    },
    {
      "start_ts": 1581.033,
      "end_ts": 1582.4,
      "peak_r": 1.21,
      "mean_r": 1.0824,
      "mass_r": 1.4793
    },
    {
      "start_ts": 1582.967,
      "end_ts": 1584.0,
      "peak_r": 1.21,
      "mean_r": 1.0903,
      "mass_r": 1.1267
    },
    {
      "start_ts": 1584.367,
      "end_ts": 1594.2,
      "peak_r": 1.83,
      "mean_r": 1.2565,
      "mass_r": 12.356
    },
    {
      "start_ts": 1594.9,
      "end_ts": 1595.633,
      "peak_r": 1.98,
      "mean_r": 1.3514,
      "mass_r": 0.991
    },
    {
      "start_ts": 1595.833,
      "end_ts": 1598.067,
      "peak_r": 1.41,
      "mean_r": 1.1575,
      "mass_r": 2.585
    },
    {
      "start_ts": 1598.3,
      "end_ts": 1599.733,
      "peak_r": 1.53,
      "mean_r": 1.2074,
      "mass_r": 1.7307
    },
    {
      "start_ts": 1600.067,
      "end_ts": 1602.8,
      "peak_r": 1.58,
      "mean_r": 1.1972,
      "mass_r": 3.2723
    },
    {
      "start_ts": 1603.733,
      "end_ts": 1604.8,
      "peak_r": 1.23,
      "mean_r": 1.1125,
      "mass_r": 1.1867
    },
    {
      "start_ts": 1606.433,
      "end_ts": 1611.133,
      "peak_r": 1.6,
      "mean_r": 1.2202,
      "mass_r": 5.735
    },
    {
      "start_ts": 1611.267,
      "end_ts": 1614.833,
      "peak_r": 1.46,
      "mean_r": 1.2495,
      "mass_r": 4.4567
    },
    {
      "start_ts": 1617.433,
      "end_ts": 1620.033,
      "peak_r": 1.51,
      "mean_r": 1.2162,
      "mass_r": 3.162
    },
    {
      "start_ts": 1620.167,
      "end_ts": 1621.367,
      "peak_r": 1.51,
      "mean_r": 1.2197,
      "mass_r": 1.4637
    },
    {
      "start_ts": 1623.9,
      "end_ts": 1624.7,
      "peak_r": 1.6,
      "mean_r": 1.305,
      "mass_r": 1.044
    },
    {
      "start_ts": 1626.067,
      "end_ts": 1631.733,
      "peak_r": 1.36,
      "mean_r": 1.0925,
      "mass_r": 6.1907
    },
    {
      "start_ts": 1632.5,
      "end_ts": 1634.167,
      "peak_r": 1.34,
      "mean_r": 1.1066,
      "mass_r": 1.8443
    },
    {
      "start_ts": 1635.267,
      "end_ts": 1637.733,
      "peak_r": 1.69,
      "mean_r": 1.3105,
      "mass_r": 3.2327
    },
    {
      "start_ts": 1640.167,
      "end_ts": 1642.867,
      "peak_r": 1.48,
      "mean_r": 1.1654,
      "mass_r": 3.1467
    },
    {
      "start_ts": 1643.667,
      "end_ts": 1645.467,
      "peak_r": 1.47,
      "mean_r": 1.2524,
      "mass_r": 2.2543
    },
    {
      "start_ts": 1647.433,
      "end_ts": 1659.3,
      "peak_r": 1.64,
      "mean_r": 1.2751,
      "mass_r": 15.1307
    },
    {
      "start_ts": 1659.9,
      "end_ts": 1661.033,
      "peak_r": 1.27,
      "mean_r": 1.1547,
      "mass_r": 1.3087
    },
    {
      "start_ts": 1662.167,
      "end_ts": 1662.867,
      "peak_r": 1.66,
      "mean_r": 1.2481,
      "mass_r": 0.8737
    },
    {
      "start_ts": 1663.4,
      "end_ts": 1664.033,
      "peak_r": 1.53,
      "mean_r": 1.2647,
      "mass_r": 0.801
    },
    {
      "start_ts": 1664.2,
      "end_ts": 1664.7,
      "peak_r": 1.41,
      "mean_r": 1.1853,
      "mass_r": 0.5927
    },
    {
      "start_ts": 1666.767,
      "end_ts": 1668.533,
      "peak_r": 1.76,
      "mean_r": 1.2266,
      "mass_r": 2.167
    },
    {
      "start_ts": 1671.767,
      "end_ts": 1675.633,
      "peak_r": 1.61,
      "mean_r": 1.2484,
      "mass_r": 4.8273
    },
    {
      "start_ts": 1678.9,
      "end_ts": 1686.467,
      "peak_r": 1.66,
      "mean_r": 1.3307,
      "mass_r": 10.069
    },
    {
      "start_ts": 1688.633,
      "end_ts": 1689.7,
      "peak_r": 1.36,
      "mean_r": 1.1497,
      "mass_r": 1.2263
    },
    {
      "start_ts": 1690.633,
      "end_ts": 1691.2,
      "peak_r": 1.41,
      "mean_r": 1.1324,
      "mass_r": 0.6417
    },
    {
      "start_ts": 1691.3,
      "end_ts": 1691.8,
      "peak_r": 1.12,
      "mean_r": 1.06,
      "mass_r": 0.53
    },
    {
      "start_ts": 1694.5,
      "end_ts": 1695.233,
      "peak_r": 1.3,
      "mean_r": 1.1759,
      "mass_r": 0.8623
    },
    {
      "start_ts": 1696.8,
      "end_ts": 1697.767,
      "peak_r": 1.19,
      "mean_r": 1.0903,
      "mass_r": 1.054
    },
    {
      "start_ts": 1698.167,
      "end_ts": 1699.367,
      "peak_r": 1.46,
      "mean_r": 1.2881,
      "mass_r": 1.5457
    },
    {
      "start_ts": 1699.8,
      "end_ts": 1707.8,
      "peak_r": 1.43,
      "mean_r": 1.1663,
      "mass_r": 9.33
    },
    {
      "start_ts": 1709.233,
      "end_ts": 1712.067,
      "peak_r": 1.26,
      "mean_r": 1.0773,
      "mass_r": 3.0523
    },
    {
      "start_ts": 1713.167,
      "end_ts": 1714.267,
      "peak_r": 2.09,
      "mean_r": 1.5958,
      "mass_r": 1.7553
    }
  ]
}