{
  "video_id": "521.3",
  "fps": 30.0,
  "total_frames": 55874,
  "total_duration_sec": 1862.467,
  "smoothing_sigma_sec": 0.133,
  "threshold": 1.0,
  "min_duration_sec": 0.5,
  "num_segments": 16,
  "total_smile_sec": 33.398,
  "segments": [
    {
      "start_ts": 66.7,
      "end_ts": 67.933,
      "peak_r": 1.43,
      "mean_r": 1.2065,
      "mass_r": 1.488
    },
    {
      "start_ts": 72.467,
      "end_ts": 73.233,
      "peak_r": 1.28,
      "mean_r": 1.1596,
      "mass_r": 0.889
    },
    {
      "start_ts": 118.433,
      "end_ts": 119.7,
      "peak_r": 1.44,
      "mean_r": 1.1811,
      "mass_r": 1.496
    },
    {
      "start_ts": 394.267,
      "end_ts": 397.0,
      "peak_r": 1.47,
      "mean_r": 1.2113,
      "mass_r": 3.311
    },
    {
      "start_ts": 448.867,
      "end_ts": 449.533,
      "peak_r": 1.26,
      "mean_r": 1.149,
      "mass_r": 0.766
    },
    {
      "start_ts": 591.967,
      "end_ts": 596.333,
      "peak_r": 1.82,
      "mean_r": 1.289,
      "mass_r": 5.6287
    },
    {
      "start_ts": 625.833,
      "end_ts": 626.6,
      "peak_r": 1.15,
      "mean_r": 1.0709,
      "mass_r": 0.821
    },
    {
      "start_ts": 627.4,
      "end_ts": 628.133,
      "peak_r": 1.18,
      "mean_r": 1.1168,
      "mass_r": 0.819
    },
    {
      "start_ts": 640.033,
      "end_ts": 640.867,
      "peak_r": 1.54,
      "mean_r": 1.3328,
      "mass_r": 1.1107
    },
    {
      "start_ts": 1046.967,
      "end_ts": 1050.533,
      "peak_r": 2.02,
      "mean_r": 1.5387,
      "mass_r": 5.488
    },
    {
      "start_ts": 1190.0,
      "end_ts": 1193.867,
      "peak_r": 1.63,
      "mean_r": 1.2394,
      "mass_r": 4.7923
    },
    {
      "start_ts": 1214.533,
      "end_ts": 1216.633,
      "peak_r": 1.82,
      "mean_r": 1.403,
      "mass_r": 2.9463
    },
    {
      "start_ts": 1285.433,
      "end_ts": 1287.733,
      "peak_r": 1.57,
      "mean_r": 1.261,
      "mass_r": 2.9003
    },
    {
      "start_ts": 1305.633,
      "end_ts": 1310.233,
      "peak_r": 1.83,
      "mean_r": 1.2718,
      "mass_r": 5.8503
    },
    {
      "start_ts": 1425.567,
      "end_ts": 1427.4,
      "peak_r": 1.39,
      "mean_r": 1.1222,
      "mass_r": 2.0573
    },
    {
      "start_ts": 1500.9,
      "end_ts": 1502.667,
      "peak_r": 1.53,
      "mean_r": 1.3136,
      "mass_r": 2.3207
    }
  ]
}